Workbook

Sheet Free cash flow
B2: Unlevered free cash flow (mm)
B3: Fiscal year | C3: 2021 | D3: 2022 | E3: 2023 | F3: 2024 | G3: 2025 | H3: 2026 | I3: 2027
B4: Revenue (Doanh thu thuần về bán hàng và cung cấp dịch vụ) | C4: 2767441385060 | D4: 2935529898990 | E4: 3228718536079 | F4: =E4*F25 -> 3164144165357 | G4: =F4*G25 -> 3489131013331 | H4: =G4*H25 -> 3847497014034 | I4: =H4*I25 -> 4242670514935
B5: COGS (Giá vốn hàng bán) | C5: 2578953875169 | D5: 2713295819602 | E5: 2999441035747 | F5: =F4*F27 -> 2937564240842 | G5: =G4*G27 -> 3239279236575 | H5: =H4*H27 -> 3571983150742 | I5: =I4*I27 -> 3938858831655
B6: Gross profit | C6: =C4-C5 -> 188487509891 | D6: =D4-D5 -> 222234079388 | E6: =E4-E5 -> 229277500332 | F6: =F4-F5 -> 226579924515 | G6: =G4-G5 -> 249851776755 | H6: =H4-H5 -> 275513863293 | I6: =I4-I5 -> 303811683280
B7: operating expense | C7: 0 | D7: 0 | E7: 0 | F7: 0 | G7: 0 | H7: 0 | I7: 0
B8: Selling, general, administrative (chi phí bán hàng) | C8: 36296206090 | D8: 40446131662 | E8: 33894216123 | F8: =F4*F28 -> 39437159623 | G8: =G4*G28 -> 43487720384 | H8: =H4*H28 -> 47954311169 | I8: =I4*I28 -> 52879662107
B9: total operating expense | C9: =SUM(C7:C8) -> 36296206090 | D9: =SUM(D7:D8) -> 40446131662 | E9: =SUM(E7:E8) -> 33894216123 | F9: =SUM(F7:F8) -> 39437159623 | G9: =SUM(G7:G8) -> 43487720384 | H9: =SUM(H7:H8) -> 47954311169 | I9: =SUM(I7:I8) -> 52879662107 | L9: 2020 | M9: 2021 | N9: 2022 | O9: 2023
B10: EBITDA | C10: =C6-C9 -> 152191303801 | D10: =D6-D9 -> 181787947726 | E10: =E6-E9 -> 195383284209 | F10: =F6-F9 -> 187142764893 | G10: =G6-G9 -> 206364056372 | H10: =H6-H9 -> 227559552124 | I10: =I6-I9 -> 250932021173 | K10: D&A | L10: -250453675286 | M10: -253302574339 | N10: -273276900980 | O10: -289499906187
B11: Appreciation & Armortization (khấu hao = giá trị hao mòn luỹ kế năm này - năm trước) | C11: =ABS(M12) -> 2848899053 | D11: =ABS(N12) -> 19974326641 | E11: =ABS(O12) -> 16223005207 | F11: ='Fixed assets'!F5 -> 10713526557 | G11: ='Fixed assets'!G5 -> 9507928181 | H11: ='Fixed assets'!H5 -> 8437996378 | I11: ='Fixed assets'!I5 -> 7488464524
B12: Operating profit (EBIT) | C12: =C10-C11 -> 149342404748 | D12: =D10-D11 -> 161813621085 | E12: =E10-E11 -> 179160279002 | F12: =F10-F11 -> 176429238335 | G12: =G10-G11 -> 196856128191 | H12: =H10-H11 -> 219121555745 | I12: =I10-I11 -> 243443556648 | M12: =M10-L10 -> -2848899053 | N12: =N10-M10 -> -19974326641 | O12: =O10-N10 -> -16223005207
B13: Operating taxes (Lợi nhuận trước thuế) | C13: 34568008955 | D13: 38732974636 | E13: 54555998716 | F13: =F12*F29 -> 45597867390 | G13: =G12*G29 -> 50877165899 | H13: =H12*H29 -> 56631631670 | I13: =I12*I29 -> 62917615684
B14: NOPAT (Net operating profit after taxes) | C14: =C12-C13 -> 114774395793 | D14: =D12-D13 -> 123080646449 | E14: =E12-E13 -> 124604280286 | F14: =F12-F13 -> 130831370945 | G14: =G12-G13 -> 145978962292 | H14: =H12-H13 -> 162489924075 | I14: =I12-I13 -> 180525940964
B15: (+) Appreciation & Armortization | C15: =C11 -> 2848899053 | D15: =D11 -> 19974326641 | E15: =E11 -> 16223005207 | F15: =F11 -> 10713526557 | G15: =G11 -> 9507928181 | H15: =H11 -> 8437996378 | I15: =I11 -> 7488464524
B16: (-) Capital expenditure | C16: ='Fixed assets'!C6 -> -17951395999 | D16: ='Fixed assets'!D6 -> 917236071 | E16: ='Fixed assets'!E6 -> 70185912 | F16: ='Fixed assets'!F6 -> -3921065312 | G16: ='Fixed assets'!G6 -> -3479825918 | H16: ='Fixed assets'!H6 -> -3088239407 | I16: ='Fixed assets'!I6 -> -2740718318
B17: (-) Change in NWC | C17: =C18-'Net working capital'!C7-'Net working capital'!C14 -> -528395938122 | D17: =D18-'Net working capital'!D7-'Net working capital'!D14 -> -451596549470 | E17: =E18-'Net working capital'!E7-'Net working capital'!E14 -> -1278398998270 | F17: =F18-'Net working capital'!F7-'Net working capital'!F14 -> -915244454257 | G17: =G18-'Net working capital'!G7-'Net working capital'!G14 -> -919963975239 | H17: =H18-'Net working capital'!H7-'Net working capital'!H14 -> -1003764515266 | I17: =I18-'Net working capital'!I7-'Net working capital'!I14 -> -1106860407512 | L17: Revenue
B18: NWC | C18: =C19-C20 -> 805734105517 | D18: =D19-D20 -> 1095372525817 | E18: =E19-E20 -> 1051664163229 | F18: =F19-F20 -> 1022558702526 | G18: =G19-G20 -> 1138283611695 | H18: =H19-H20 -> 1255195858335 | I18: =I19-I20 -> 1384116073177 | K18: 2020 | L18: 2767441385060
B19: Current Assets | C19: ='Net working capital'!D7 -> 1176351590402 | D19: ='Net working capital'!E7 -> 1712717843658 | E19: ='Net working capital'!F7 -> 1494733660006 | F19: ='Net working capital'!G7 -> 1540403144730 | G19: ='Net working capital'!H7 -> 1698621992648 | H19: ='Net working capital'!I7 -> 1873086169512 | I19: ='Net working capital'!J7 -> 2065469429692 | K19: 2021 | L19: 2178704787315
B20: Current liabilities | C20: ='Net working capital'!D14 -> 370617484885 | D20: ='Net working capital'!E14 -> 617345317841 | E20: ='Net working capital'!F14 -> 443069496777 | F20: ='Net working capital'!G14 -> 517844442204 | G20: ='Net working capital'!H14 -> 560338380953 | H20: ='Net working capital'!I14 -> 617890311177 | I20: ='Net working capital'!J14 -> 681353356515
B21: Unlevered free cash flow (FCFC) | C21: =C14+C15-C16-C17 -> 663970628967 | D21: =D14+D15-D16-D17 -> 593734286489 | E21: =E14+E15-E16-E17 -> 1419156097851 | F21: =F14+F15-F16-F17 -> 1060710417072 | G21: =G14+G15-G16-G17 -> 1078930691629 | H21: =H14+H15-H16-H17 -> 1177780675127 | I21: =I14+I15-I16-I17 -> 1297615531319
B23: Assumption
B24: Fiscal year | C24: 2021 | D24: 2022 | E24: 2023 | F24: 2024 | G24: 2025 | H24: 2026 | I24: 2027
B25: Revenue growth | C25: =L18/L19 -> 1.2702232 | D25: =D4/C4 -> 1.0607379 | E25: =E4/D4 -> 1.0998759 | F25: =0.98 -> 0.98 | G25: =AVERAGE($C$25:$F$25) -> 1.1027092 | H25: =AVERAGE($C$25:$F$25) -> 1.1027092 | I25: =AVERAGE($C$25:$F$25) -> 1.1027092
B27: COGS% of Revenue | C27: =C5/C4 -> 0.93189106 | D27: =D5/D4 -> 0.92429507 | E27: =E5/E4 -> 0.92898808 | F27: =AVERAGE($C$27:$E$27) -> 0.9283914 | G27: =AVERAGE($C$27:$E$27) -> 0.9283914 | H27: =AVERAGE($C$27:$E$27) -> 0.9283914 | I27: =AVERAGE($C$27:$E$27) -> 0.9283914
B28: SG&A% of Revenue | C28: =C8/C4 -> 0.013115438 | D28: =D8/D4 -> 0.013778136 | E28: =E8/E4 -> 0.01049773 | F28: =AVERAGE($C$28:$E$28) -> 0.012463768 | G28: =AVERAGE($C$28:$E$28) -> 0.012463768 | H28: =AVERAGE($C$28:$E$28) -> 0.012463768 | I28: =AVERAGE($C$28:$E$28) -> 0.012463768
B29: Tax% of EBIT | C29: =C13/C12 -> 0.23146814 | D29: =D13/D12 -> 0.23936783 | E29: =E13/E12 -> 0.30450945 | F29: =AVERAGE($C$29:$E$29) -> 0.25844847 | G29: =AVERAGE($C$29:$E$29) -> 0.25844847 | H29: =AVERAGE($C$29:$E$29) -> 0.25844847 | I29: =AVERAGE($C$29:$E$29) -> 0.25844847

Sheet Fixed assets
B2: Fixed assets schedule
B3: Fiscal year | C3: 2021 | D3: 2022 | E3: 2023 | F3: 2024 | G3: 2025 | H3: 2026 | I3: 2027
B4: Beginning PP&E | C4: 186060221314 | D4: =C7 -> 165259926262 | E4: =D7 -> 146202835692 | F4: =E7 -> 130050016397 | G4: =F7 -> 115415424527 | H4: =G7 -> 102427670429 | I4: =H7 -> 90901434643
B5: D&A | C5: 2848899053 | D5: 19974326641 | E5: 16223005207 | F5: =F4*F11 -> 10713526557 | G5: =G4*G11 -> 9507928181 | H5: =H4*H11 -> 8437996378 | I5: =I4*I11 -> 7488464524
B6: _x0008_CapEX = End - Begin + D&A | C6: =C7-C4+C5 -> -17951395999 | D6: =D7-D4+D5 -> 917236071 | E6: =E7-E4+E5 -> 70185912 | F6: =F12*F4 -> -3921065312 | G6: =G12*G4 -> -3479825918 | H6: =H12*H4 -> -3088239407 | I6: =I12*I4 -> -2740718318
B7: _x0008_Ending PP&E | C7: 165259926262 | D7: 146202835692 | E7: 130050016397 | F7: =F6+F4-F5 -> 115415424527 | G7: =G6+G4-G5 -> 102427670429 | H7: =H6+H4-H5 -> 90901434643 | I7: =I6+I4-I5 -> 80672251801
B9: _x0008_Assumption
B10: _x0008__x0008_Fiscal year | C10: 2021 | D10: 2022 | E10: 2023 | F10: 2024 | G10: 2025 | H10: 2026 | I10: 2027
B11: _x0008_D&A at % beginning PP&E | C11: =C5/C4 -> 0.015311704 | D11: =D5/D4 -> 0.12086612 | E11: =E5/E4 -> 0.11096232 | F11: =AVERAGE($C$11:$E$11) -> 0.082380048 | G11: =AVERAGE($C$11:$E$11) -> 0.082380048 | H11: =AVERAGE($C$11:$E$11) -> 0.082380048 | I11: =AVERAGE($C$11:$E$11) -> 0.082380048
B12: CapEx at % PP&E | C12: =C6/C4 -> -0.096481644 | D12: =D6/D4 -> 0.0055502631 | E12: =E6/E4 -> 0.00048005849 | F12: =AVERAGE($C$12:$E$12) -> -0.030150441 | G12: =AVERAGE($C$12:$E$12) -> -0.030150441 | H12: =AVERAGE($C$12:$E$12) -> -0.030150441 | I12: =AVERAGE($C$12:$E$12) -> -0.030150441

Sheet Net working capital
B2: NWC
B3: Fiscal year | C3: 2020 | D3: 2021 | E3: 2022 | F3: 2023 | G3: 2024 | H3: 2025 | I3: 2026 | J3: 2027
B4: Account receivable (Các khoản phải thu ngắn hạn) | C4: 840273849720 | D4: 912990601451 | E4: 1337797171092 | F4: 1158165965650 | G4: =G21*G19/365 -> 1207530425856 | H4: =H21*H19/365 -> 1331554960271 | I4: =I21*I19/365 -> 1468317960573 | J4: =J21*J19/365 -> 1619127784933
B5: Merchandised inventory (hàng tồn kho) | C5: 163776078943 | D5: 256946359992 | E5: 363952017300 | F5: 318396620320 | G5: =G22*G19/365 -> 332846102300 | H5: =H22*H19/365 -> 367032473083 | I5: =I22*I19/365 -> 404730100087 | J5: =J22*J19/365 -> 446299621775
B6: Other current assets | C6: 3395017804 | D6: 6414628959 | E6: 10968655266 | F6: 18171074036 | G6: =G19*G25/365 -> 26616574 | H6: =H19*H25/365 -> 34559294 | I6: =I19*I25/365 -> 38108853 | J6: =J19*J25/365 -> 42022984
B7: Current assets | C7: =SUM(C4:C6) -> 1007444946467 | D7: =SUM(D4:D6) -> 1176351590402 | E7: =SUM(E4:E6) -> 1712717843658 | F7: =SUM(F4:F6) -> 1494733660006 | G7: =SUM(G4:G6) -> 1540403144730 | H7: =SUM(H4:H6) -> 1698621992648 | I7: =SUM(I4:I6) -> 1873086169512 | J7: =SUM(J4:J6) -> 2065469429692
B9: Account payable ( Nợ phải trả người bán ngắn hạn) | C9: 201276174640 | D9: 239425736234 | E9: 479526147585 | F9: 313174345331 | G9: =G19*G23/365 -> 366197934119 | H9: =H19*H23/365 -> 403809846258 | I9: =I19*I23/365 -> 445284849374 | J9: =J19*J23/365 -> 491019718610
B10: Accrued salaries and benefits (Nợ phải trả người lao động) | C10: 21381700463 | D10: 13425965039 | E10: 12869887553 | F10: 18097259395 | G10: =G18*G26 -> 19443310690 | H10: =H18*H26 -> 17260346235 | I10: =I18*I26 -> 19033143309 | J10: =J18*J26 -> 20988023026
B11: Accrued membership rewards (Quỹ khen thưởng và phúc lợi) | C11: 8642308995 | D11: 2277982083 | E11: 669687252 | F11: 32674595 | G11: =G27*G18 -> 3953412091 | H11: =H27*H18 -> 1234440775 | I11: =I27*I18 -> 1361229251 | J11: =J27*J18 -> 1501040075
B12: Deferred memberships fees (Người mua trả tiền trước ngắn hạn) | C12: 90416308108 | D12: 110724990085 | E12: 116471108093 | F12: 108174426424 | G12: =G18*G28 -> 122114322069 | H12: =H18*H28 -> 131644974481 | I12: =I18*I28 -> 145166129989 | J12: =J18*J28 -> 160076033126
B13: Other current liabilities ( Nợ phải trả ngắn hạn khác) | C13: 4968604966 | D13: 4762811444 | E13: 7808487358 | F13: 3590791032 | G13: =G29*G18 -> 6135463235 | H13: =H29*H18 -> 6388773203 | I13: =I29*I18 -> 7044959255 | J13: =J29*J18 -> 7768541678
B14: Current liabilites | C14: =SUM(C9:C13) -> 326685097172 | D14: =SUM(D9:D13) -> 370617484885 | E14: =SUM(E9:E13) -> 617345317841 | F14: =SUM(F9:F13) -> 443069496777 | G14: =SUM(G9:G13) -> 517844442204 | H14: =SUM(H9:H13) -> 560338380953 | I14: =SUM(I9:I13) -> 617890311177 | J14: =SUM(J9:J13) -> 681353356515
B16: Assumption
B17: Fiscal year | C17: 2020 | D17: 2021 | E17: 2022 | F17: 2023 | G17: 2024 | H17: 2025 | I17: 2026 | J17: 2027
B18: Revenue | C18: 2195498487388 | D18: 2767441385060 | E18: 2935529898990 | F18: 3228718536079 | G18: 3.1641442e+12 | H18: 3.489131e+12 | I18: 3.847497e+12 | J18: 4.2426705e+12
B19: COGS | C19: 1992377348652 | D19: 2578953875169 | E19: 2713295819602 | F19: 2999441035747 | G19: 2.9375642e+12 | H19: 3.2392792e+12 | I19: 3.5719832e+12 | J19: 3.9388588e+12
B21: Daily sales Outstanding (DSO) | C21: =C4/C19 *365 -> 153.93668 | D21: =D4/D19 *365 -> 129.21579 | E21: =E4/E19 *365 -> 179.96415 | F21: =F4/F19 *365 -> 140.93645 | G21: =AVERAGE($D$21:$F$21) -> 150.0388 | H21: =AVERAGE($D$21:$F$21) -> 150.0388 | I21: =AVERAGE($D$21:$F$21) -> 150.0388 | J21: =AVERAGE($D$21:$F$21) -> 150.0388
B22: Daily inventory Outstanding (DIO) | C22: =C5/C19 *365 -> 30.003487 | D22: =D5/D19 *365 -> 36.365684 | E22: =E5/E19 *365 -> 48.959824 | F22: =F5/F19 *365 -> 38.745475 | G22: =AVERAGE($D$22:$F$22) -> 41.356994 | H22: =AVERAGE($D$22:$F$22) -> 41.356994 | I22: =AVERAGE($D$22:$F$22) -> 41.356994 | J22: =AVERAGE($D$22:$F$22) -> 41.356994
B23: Daily payable Outstanding (DPO) | C23: =C9/C19 *365 -> 36.873439 | D23: =D9/D19 *365 -> 33.885986 | E23: =E9/E19 *365 -> 64.507173 | F23: =F9/F19 *365 -> 38.109979 | G23: =AVERAGE($D$23:$F$23) -> 45.501046 | H23: =AVERAGE($D$23:$F$23) -> 45.501046 | I23: =AVERAGE($D$23:$F$23) -> 45.501046 | J23: =AVERAGE($D$23:$F$23) -> 45.501046
B25: Other current assets | C25: =C6/C18 -> 0.001546354 | D25: =D6/D18 -> 0.0023178915 | E25: =E6/E18 -> 0.0037365163 | F25: =F6/F18 -> 0.0056279523 | G25: =AVERAGE($C$25:$F$25) -> 0.0033071785 | H25: =AVERAGE($D$25:$F$25) -> 0.0038941201 | I25: =AVERAGE($D$25:$F$25) -> 0.0038941201 | J25: =AVERAGE($D$25:$F$25) -> 0.0038941201
B26: Accrued salaries and benefits at % of revenue | C26: =C10/C18 -> 0.0097388819 | D26: =D10/D18 -> 0.0048514 | E26: =E10/E18 -> 0.0043841787 | F26: =F10/F18 -> 0.0056050904 | G26: =AVERAGE($C$26:$F$26) -> 0.0061448877 | H26: =AVERAGE($D$26:$F$26) -> 0.0049468897 | I26: =AVERAGE($D$26:$F$26) -> 0.0049468897 | J26: =AVERAGE($D$26:$F$26) -> 0.0049468897
B27: Accrued membership rewards at % of revenue | C27: =C11/C18 -> 0.0039363767 | D27: =D11/D18 -> 0.00082313652 | E27: =E11/E18 -> 0.00022813164 | F27: =F11/F18 -> 1.0119989e-05 | G27: =AVERAGE($C$27:$F$27) -> 0.0012494412 | H27: =AVERAGE($D$27:$F$27) -> 0.00035379605 | I27: =AVERAGE($D$27:$F$27) -> 0.00035379605 | J27: =AVERAGE($D$27:$F$27) -> 0.00035379605
B28: Deferred memberships fees at % of revenue | C28: =C12/C18 -> 0.041182587 | D28: =D12/D18 -> 0.040009877 | E28: =E12/E18 -> 0.039676349 | F28: =F12/F18 -> 0.033503827 | G28: =AVERAGE($C$28:$F$28) -> 0.03859316 | H28: =AVERAGE($D$28:$F$28) -> 0.037730018 | I28: =AVERAGE($D$28:$F$28) -> 0.037730018 | J28: =AVERAGE($D$28:$F$28) -> 0.037730018
B29: Other current liabilities at % of revenue | C29: =C13/C18 -> 0.0022630874 | D29: =D13/D18 -> 0.0017210162 | E29: =E13/E18 -> 0.0026599924 | F29: =F13/F18 -> 0.0011121412 | G29: =AVERAGE($C$29:$F$29) -> 0.0019390593 | H29: =AVERAGE($D$29:$F$29) -> 0.00183105 | I29: =AVERAGE($D$29:$F$29) -> 0.00183105 | J29: =AVERAGE($D$29:$F$29) -> 0.00183105

Sheet WACC
B2: Weighted average cost of assets (WACC)
B3: Equity | C3: 1049722021727
B4: Debt | C4: 1422318486560
B6: Risk-free rate (10yr Treasury Yield) | C6: 0.05
B7: Excess CDS spread | C7: 0.0184
B8: Cost of debt | C8: =C7+C6 -> 0.0684
B9: Tax rate (Oil+gas: 25-50%, Khác:20%) | C9: 0.35
B10: D/(D+E) | C10: =C4/(C4+C3) -> 0.57536213
B11: After tax cost of debt | C11: =C8*(1-C9) -> 0.04446
B13: Risk-free rate (10yr Treasury Yield) | C13: 0.05
B14: Market premium | C14: 0.09
B15: Levered beta | C15: 0.67
B16: E/(D+E) | C16: =C3/(C4+C3) -> 0.42463787
B17: Cost of Equity | C17: =C13+C14*C15 -> 0.1103
B18: WACC | C18: =C17*C16+C11*C10 -> 0.072418158

Sheet DCF
B2: Unlevered free cash flow
B3: Fiscal Year | C3: 2021 | D3: 2022 | E3: 2023 | F3: 2024 | G3: 2025 | H3: 2026 | I3: 2027
B4: Unlevered free cash flow | C4: ='Free cash flow'!C21 -> 663970628967 | D4: ='Free cash flow'!D21 -> 593734286489 | E4: ='Free cash flow'!E21 -> 1419156097851 | F4: ='Free cash flow'!F21 -> 1060710417072 | G4: ='Free cash flow'!G21 -> 1078930691629 | H4: ='Free cash flow'!H21 -> 1177780675127 | I4: ='Free cash flow'!I21 -> 1297615531319
B6: Projection Year | F6: 1 | G6: 2 | H6: 3 | I6: 4
B7: Present value of free cash flow | F7: =F4/(1+$C$12)^F6 -> 989082858809 | G7: =G4/(1+$C$12)^G6 -> 938134765105 | H7: =H4/(1+$C$12)^H6 -> 954930904048 | I7: =I4/(1+$C$12)^I6 -> 981046066290
B9: Implied Share price calculation
B10: Sum PV of FCF | C10: =SUM(F7:I7) -> 3863194594253
B11: Growth rate | C11: 0.0642
B12: WACC | C12: =WACC!C18 -> 0.072418158
B13: Terminal value | C13: =I4*(1+C11)*(C12-C11) -> 11348638195
B14: PV of terminal value | C14: =C13/(1+C12)^4 -> 8579996609
B15: Enterprise value | C15: =C14+C10 -> 3871774590863
B16: (+) Cash | C16: 649484816227
B17: (-) Debt | C17: 1422318486560
B18: (-) Minority interest | C18: 107914630936
B19: Equity value | C19: =C15+C16-C17-C18 -> 2991026289594
B20: Diluted Share Outstanding (mm) | C20: 81194463
B21: Implied Share price | C21: =C19/C20 -> 36837.811
