Workbook

Sheet Inputs
A1: Portfolio Project Inputs
A2: Blue-font cells are editable assumptions. The workbook recalculates automatically.
A4: Assumption | B4: Value | D4: Manual allocation | E4: Weight | G4: DCA Projection Assumptions
A5: Annual risk-free rate | B5: 0.045 | D5: VESAF | E5: 0.2 | G5: Assumption | H5: Value | I5: Notes
A6: Initial investment | B6: 10000000 | D6: DCDS | E6: 0.25 | G6: DCA start date | H6: 46023 | I6: Investment begins in January 2026.
A7: Monthly DCA contribution | B7: 10000000 | D7: SSISCA | E7: 0.1 | G7: Projection horizon (months) | H7: 120 | I7: Jan-2026 through Dec-2035.
A8: Monte Carlo horizon (months) | B8: 120 | D8: VCBF-BCF | E8: 0.3 | G8: Future portfolio annual return | H8: 0.12 | I8: Illustrative base case; editable.
A9: Monte Carlo simulations | B9: 5000 | D9: MAGEF | E9: 0.15 | G9: Future VN-Index annual return | H9: 0.1 | I9: Illustrative base case; editable.
A10: Minimum fund weight | B10: 0 | D10: Total | E10: =SUM(E5:E9) -> 1 | G10: Actual data end date | H10: ='NAV Data'!A34 -> 46204 | I10: Linked to the final date in NAV Data.
A11: Maximum fund weight | B11: 0.4 | G11: Contribution timing | H11: Month-end | I11: Initial investment in Jan-2026; monthly DCA begins Feb-2026.
D13: Start with the Dashboard sheet for the executive summary.
A14: Model conventions
A15: Data frequency | B15: Monthly NAV/index levels from Jan-2024 to Jul-2026.
A16: Optimization | B16: Long-only; weights sum to 100%; each fund capped at 40%.
A17: Expected returns | B17: Historical CAGR over the available period.
A18: Risk | B18: Annualized sample standard deviation of monthly returns.
A19: Monte Carlo | B19: GBM-style simulation with a fixed random seed; monthly DCA is added at month-end.
A20: Important limitation | B20: 31 observations is a short sample. Results are illustrative, not investment advice.

Sheet NAV Data
A1: Monthly Fund NAV and VN-Index
A3: Date | B3: VESAF | C3: DCDS | D3: SSISCA | E3: VCBF-BCF | F3: MAGEF | G3: VN-Index
A4: 45292 | B4: 25832.28 | C4: 65931.49 | D4: 30576.68 | E4: 28149.36 | F4: 13886.81 | G4: 1131.72
A5: 45323 | B5: 26940.13 | C5: 67721.91 | D5: 32520.44 | E5: 29547.29 | F5: 14517.13 | G5: 1173.02
A6: 45352 | B6: 27994.11 | C6: 72191.61 | D6: 34511.64 | E6: 32183.48 | F6: 15614.61 | G6: 1258.28
A7: 45383 | B7: 29462.88 | C7: 76061.71 | D7: 36405.25 | E7: 32987.54 | F7: 16377.91 | G7: 1281.52
A8: 45413 | B8: 28203.64 | C8: 72945.92 | D8: 35334.54 | E8: 31321.15 | F8: 15589.97 | G8: 1216.36
A9: 45444 | B9: 30147.87 | C9: 79286.75 | D9: 38207.65 | E9: 33534.73 | F9: 16706.4 | G9: 1280
A10: 45474 | B10: 30456.57 | C10: 79515.4 | D10: 38840.16 | E10: 33473.78 | F10: 16681.94 | G10: 1254.56
A11: 45505 | B11: 30514.89 | C11: 76470.06 | D11: 38913.74 | E11: 33368.61 | F11: 16317.11 | G11: 1226.96
A12: 45536 | B12: 31050.21 | C12: 80598.96 | D12: 39790.39 | E12: 34243.81 | F12: 17090.07 | G12: 1275.8
A13: 45566 | B13: 31127.08 | C13: 80845.87 | D13: 40115.57 | E13: 35051.24 | F13: 17168.24 | G13: 1292.2
A14: 45597 | B14: 30787.01 | C14: 79396.4 | D14: 39562.59 | E14: 34441.56 | F14: 16887.96 | G14: 1254.89
A15: 45627 | B15: 30731.43 | C15: 79311.46 | D15: 39716.89 | E15: 34815.79 | F15: 16684.64 | G15: 1251.21
... A34: 46204 | B34: 33322.89 | C34: 100667.85 | D34: 43813.68 | E34: 43501.31 | F34: 21765.73 | G34: 1867.21

Sheet Monthly Returns
A1: Monthly Return, Growth and Drawdown Engine
A2: Returns, normalized growth, running peaks, drawdowns and excess returns versus VN-Index.
A4: Date | B4: VESAF | C4: DCDS | D4: SSISCA | E4: VCBF-BCF | F4: MAGEF | G4: VN-Index | I4: Growth Index | J4: VESAF | K4: DCDS | L4: SSISCA | M4: VCBF-BCF | N4: MAGEF | O4: VN-Index | Q4: Running Peak | R4: VESAF | S4: DCDS | T4: SSISCA | U4: VCBF-BCF | V4: MAGEF | W4: VN-Index | Y4: Drawdown | Z4: VESAF | AA4: DCDS | AB4: SSISCA | AC4: VCBF-BCF | AD4: MAGEF | AE4: VN-Index | AG4: Date | AH4: VESAF | AI4: DCDS | AJ4: SSISCA | AK4: VCBF-BCF | AL4: MAGEF
A5: 45292 | I5: 45292 | J5: 100 | K5: 100 | L5: 100 | M5: 100 | N5: 100 | O5: 100 | Q5: 45292 | R5: =J5 -> 100 | S5: =K5 -> 100 | T5: =L5 -> 100 | U5: =M5 -> 100 | V5: =N5 -> 100 | W5: =O5 -> 100 | Y5: 45292 | Z5: =J5/R5-1 -> 0 | AA5: =K5/S5-1 -> 0 | AB5: =L5/T5-1 -> 0 | AC5: =M5/U5-1 -> 0 | AD5: =N5/V5-1 -> 0 | AE5: =O5/W5-1 -> 0 | AG5: 45292
A6: 45323 | B6: ='NAV Data'!B5/'NAV Data'!B4-1 -> 0.042886265 | C6: ='NAV Data'!C5/'NAV Data'!C4-1 -> 0.027155764 | D6: ='NAV Data'!D5/'NAV Data'!D4-1 -> 0.063570015 | E6: ='NAV Data'!E5/'NAV Data'!E4-1 -> 0.049661165 | F6: ='NAV Data'!F5/'NAV Data'!F4-1 -> 0.045389834 | G6: ='NAV Data'!G5/'NAV Data'!G4-1 -> 0.036493126 | I6: 45323 | J6: =J5*(1+B6) -> 104.28863 | K6: =K5*(1+C6) -> 102.71558 | L6: =L5*(1+D6) -> 106.357 | M6: =M5*(1+E6) -> 104.96612 | N6: =N5*(1+F6) -> 104.53898 | O6: =O5*(1+G6) -> 103.64931 | Q6: 45323 | R6: =MAX(R5,J6) -> 104.28863 | S6: =MAX(S5,K6) -> 102.71558 | T6: =MAX(T5,L6) -> 106.357 | U6: =MAX(U5,M6) -> 104.96612 | V6: =MAX(V5,N6) -> 104.53898 | W6: =MAX(W5,O6) -> 103.64931 | Y6: 45323 | Z6: =J6/R6-1 -> 0 | AA6: =K6/S6-1 -> 0 | AB6: =L6/T6-1 -> 0 | AC6: =M6/U6-1 -> 0 | AD6: =N6/V6-1 -> 0 | AE6: =O6/W6-1 -> 0 | AG6: 45323 | AH6: =B6-$G6 -> 0.0063931393 | AI6: =C6-$G6 -> -0.0093373612 | AJ6: =D6-$G6 -> 0.027076889 | AK6: =E6-$G6 -> 0.013168039 | AL6: =F6-$G6 -> 0.0088967084
A7: 45352 | B7: ='NAV Data'!B6/'NAV Data'!B5-1 -> 0.039123048 | C7: ='NAV Data'!C6/'NAV Data'!C5-1 -> 0.066000796 | D7: ='NAV Data'!D6/'NAV Data'!D5-1 -> 0.061229184 | E7: ='NAV Data'!E6/'NAV Data'!E5-1 -> 0.08921935 | F7: ='NAV Data'!F6/'NAV Data'!F5-1 -> 0.075598965 | G7: ='NAV Data'!G6/'NAV Data'!G5-1 -> 0.072684183 | I7: 45352 | J7: =J6*(1+B7) -> 108.36872 | K7: =K6*(1+C7) -> 109.49489 | L7: =L6*(1+D7) -> 112.86915 | M7: =M6*(1+E7) -> 114.33113 | N7: =N6*(1+F7) -> 112.44202 | O7: =O6*(1+G7) -> 111.18298 | Q7: 45352 | R7: =MAX(R6,J7) -> 108.36872 | S7: =MAX(S6,K7) -> 109.49489 | T7: =MAX(T6,L7) -> 112.86915 | U7: =MAX(U6,M7) -> 114.33113 | V7: =MAX(V6,N7) -> 112.44202 | W7: =MAX(W6,O7) -> 111.18298 | Y7: 45352 | Z7: =J7/R7-1 -> 0 | AA7: =K7/S7-1 -> 0 | AB7: =L7/T7-1 -> 0 | AC7: =M7/U7-1 -> 0 | AD7: =N7/V7-1 -> 0 | AE7: =O7/W7-1 -> 0 | AG7: 45352 | AH7: =B7-$G7 -> -0.033561135 | AI7: =C7-$G7 -> -0.0066833862 | AJ7: =D7-$G7 -> -0.011454999 | AK7: =E7-$G7 -> 0.016535167 | AL7: =F7-$G7 -> 0.0029147821
A8: 45383 | B8: ='NAV Data'!B7/'NAV Data'!B6-1 -> 0.052467108 | C8: ='NAV Data'!C7/'NAV Data'!C6-1 -> 0.053608723 | D8: ='NAV Data'!D7/'NAV Data'!D6-1 -> 0.054868734 | E8: ='NAV Data'!E7/'NAV Data'!E6-1 -> 0.024983625 | F8: ='NAV Data'!F7/'NAV Data'!F6-1 -> 0.048883706 | G8: ='NAV Data'!G7/'NAV Data'!G6-1 -> 0.018469657 | I8: 45383 | J8: =J7*(1+B8) -> 114.05451 | K8: =K7*(1+C8) -> 115.36477 | L8: =L7*(1+D8) -> 119.06214 | M8: =M7*(1+E8) -> 117.18753 | N8: =N7*(1+F8) -> 117.93861 | O8: =O7*(1+G8) -> 113.23649 | Q8: 45383 | R8: =MAX(R7,J8) -> 114.05451 | S8: =MAX(S7,K8) -> 115.36477 | T8: =MAX(T7,L8) -> 119.06214 | U8: =MAX(U7,M8) -> 117.18753 | V8: =MAX(V7,N8) -> 117.93861 | W8: =MAX(W7,O8) -> 113.23649 | Y8: 45383 | Z8: =J8/R8-1 -> 0 | AA8: =K8/S8-1 -> 0 | AB8: =L8/T8-1 -> 0 | AC8: =M8/U8-1 -> 0 | AD8: =N8/V8-1 -> 0 | AE8: =O8/W8-1 -> 0 | AG8: 45383 | AH8: =B8-$G8 -> 0.033997451 | AI8: =C8-$G8 -> 0.035139066 | AJ8: =D8-$G8 -> 0.036399077 | AK8: =E8-$G8 -> 0.0065139681 | AL8: =F8-$G8 -> 0.030414049
A9: 45413 | B9: ='NAV Data'!B8/'NAV Data'!B7-1 -> -0.042739882 | C9: ='NAV Data'!C8/'NAV Data'!C7-1 -> -0.040963975 | D9: ='NAV Data'!D8/'NAV Data'!D7-1 -> -0.029410868 | E9: ='NAV Data'!E8/'NAV Data'!E7-1 -> -0.05051574 | F9: ='NAV Data'!F8/'NAV Data'!F7-1 -> -0.048109924 | G9: ='NAV Data'!G8/'NAV Data'!G7-1 -> -0.050845871 | I9: 45413 | J9: =J8*(1+B9) -> 109.17983 | K9: =K8*(1+C9) -> 110.63897 | L9: =L8*(1+D9) -> 115.56042 | M9: =M8*(1+E9) -> 111.26772 | N9: =N8*(1+F9) -> 112.26459 | O9: =O8*(1+G9) -> 107.47888 | Q9: 45413 | R9: =MAX(R8,J9) -> 114.05451 | S9: =MAX(S8,K9) -> 115.36477 | T9: =MAX(T8,L9) -> 119.06214 | U9: =MAX(U8,M9) -> 117.18753 | V9: =MAX(V8,N9) -> 117.93861 | W9: =MAX(W8,O9) -> 113.23649 | Y9: 45413 | Z9: =J9/R9-1 -> -0.042739882 | AA9: =K9/S9-1 -> -0.040963975 | AB9: =L9/T9-1 -> -0.029410868 | AC9: =M9/U9-1 -> -0.05051574 | AD9: =N9/V9-1 -> -0.048109924 | AE9: =O9/W9-1 -> -0.050845871 | AG9: 45413 | AH9: =B9-$G9 -> 0.008105989 | AI9: =C9-$G9 -> 0.0098818954 | AJ9: =D9-$G9 -> 0.021435003 | AK9: =E9-$G9 -> 0.00033013034 | AL9: =F9-$G9 -> 0.0027359469
A10: 45444 | B10: ='NAV Data'!B9/'NAV Data'!B8-1 -> 0.068935428 | C10: ='NAV Data'!C9/'NAV Data'!C8-1 -> 0.086925081 | D10: ='NAV Data'!D9/'NAV Data'!D8-1 -> 0.081311657 | E10: ='NAV Data'!E9/'NAV Data'!E8-1 -> 0.07067365 | F10: ='NAV Data'!F9/'NAV Data'!F8-1 -> 0.071612069 | G10: ='NAV Data'!G9/'NAV Data'!G8-1 -> 0.052320037 | I10: 45444 | J10: =J9*(1+B10) -> 116.70619 | K10: =K9*(1+C10) -> 120.25627 | L10: =L9*(1+D10) -> 124.95683 | M10: =M9*(1+E10) -> 119.13141 | N10: =N9*(1+F10) -> 120.30409 | O10: =O9*(1+G10) -> 113.10218 | Q10: 45444 | R10: =MAX(R9,J10) -> 116.70619 | S10: =MAX(S9,K10) -> 120.25627 | T10: =MAX(T9,L10) -> 124.95683 | U10: =MAX(U9,M10) -> 119.13141 | V10: =MAX(V9,N10) -> 120.30409 | W10: =MAX(W9,O10) -> 113.23649 | Y10: 45444 | Z10: =J10/R10-1 -> 0 | AA10: =K10/S10-1 -> 0 | AB10: =L10/T10-1 -> 0 | AC10: =M10/U10-1 -> 0 | AD10: =N10/V10-1 -> 0 | AE10: =O10/W10-1 -> -0.0011860915 | AG10: 45444 | AH10: =B10-$G10 -> 0.016615391 | AI10: =C10-$G10 -> 0.034605044 | AJ10: =D10-$G10 -> 0.02899162 | AK10: =E10-$G10 -> 0.018353613 | AL10: =F10-$G10 -> 0.019292032
A11: 45474 | B11: ='NAV Data'!B10/'NAV Data'!B9-1 -> 0.010239529 | C11: ='NAV Data'!C10/'NAV Data'!C9-1 -> 0.0028838362 | D11: ='NAV Data'!D10/'NAV Data'!D9-1 -> 0.016554538 | E11: ='NAV Data'!E10/'NAV Data'!E9-1 -> -0.0018175187 | F11: ='NAV Data'!F10/'NAV Data'!F9-1 -> -0.0014641096 | G11: ='NAV Data'!G10/'NAV Data'!G9-1 -> -0.019875 | I11: 45474 | J11: =J10*(1+B11) -> 117.90121 | K11: =K10*(1+C11) -> 120.60307 | L11: =L10*(1+D11) -> 127.02543 | M11: =M10*(1+E11) -> 118.91489 | N11: =N10*(1+F11) -> 120.12795 | O11: =O10*(1+G11) -> 110.85427 | Q11: 45474 | R11: =MAX(R10,J11) -> 117.90121 | S11: =MAX(S10,K11) -> 120.60307 | T11: =MAX(T10,L11) -> 127.02543 | U11: =MAX(U10,M11) -> 119.13141 | V11: =MAX(V10,N11) -> 120.30409 | W11: =MAX(W10,O11) -> 113.23649 | Y11: 45474 | Z11: =J11/R11-1 -> 0 | AA11: =K11/S11-1 -> 0 | AB11: =L11/T11-1 -> 0 | AC11: =M11/U11-1 -> -0.0018175187 | AD11: =N11/V11-1 -> -0.0014641096 | AE11: =O11/W11-1 -> -0.021037518 | AG11: 45474 | AH11: =B11-$G11 -> 0.030114529 | AI11: =C11-$G11 -> 0.022758836 | AJ11: =D11-$G11 -> 0.036429538 | AK11: =E11-$G11 -> 0.018057481 | AL11: =F11-$G11 -> 0.01841089
A12: 45505 | B12: ='NAV Data'!B11/'NAV Data'!B10-1 -> 0.0019148578 | C12: ='NAV Data'!C11/'NAV Data'!C10-1 -> -0.038298745 | D12: ='NAV Data'!D11/'NAV Data'!D10-1 -> 0.0018944309 | E12: ='NAV Data'!E11/'NAV Data'!E10-1 -> -0.0031418621 | F12: ='NAV Data'!F11/'NAV Data'!F10-1 -> -0.021869759 | G12: ='NAV Data'!G11/'NAV Data'!G10-1 -> -0.021999745 | I12: 45505 | J12: =J11*(1+B12) -> 118.12697 | K12: =K11*(1+C12) -> 115.98412 | L12: =L11*(1+D12) -> 127.26607 | M12: =M11*(1+E12) -> 118.54127 | N12: =N11*(1+F12) -> 117.50078 | O12: =O11*(1+G12) -> 108.41551 | Q12: 45505 | R12: =MAX(R11,J12) -> 118.12697 | S12: =MAX(S11,K12) -> 120.60307 | T12: =MAX(T11,L12) -> 127.26607 | U12: =MAX(U11,M12) -> 119.13141 | V12: =MAX(V11,N12) -> 120.30409 | W12: =MAX(W11,O12) -> 113.23649 | Y12: 45505 | Z12: =J12/R12-1 -> 0 | AA12: =K12/S12-1 -> -0.038298745 | AB12: =L12/T12-1 -> 0 | AC12: =M12/U12-1 -> -0.0049536704 | AD12: =N12/V12-1 -> -0.023301848 | AE12: =O12/W12-1 -> -0.042574443 | AG12: 45505 | AH12: =B12-$G12 -> 0.023914603 | AI12: =C12-$G12 -> -0.016299 | AJ12: =D12-$G12 -> 0.023894176 | AK12: =E12-$G12 -> 0.018857883 | AL12: =F12-$G12 -> 0.00012998638
A13: 45536 | B13: ='NAV Data'!B12/'NAV Data'!B11-1 -> 0.017542911 | C13: ='NAV Data'!C12/'NAV Data'!C11-1 -> 0.053993681 | D13: ='NAV Data'!D12/'NAV Data'!D11-1 -> 0.022528033 | E13: ='NAV Data'!E12/'NAV Data'!E11-1 -> 0.026228243 | F13: ='NAV Data'!F12/'NAV Data'!F11-1 -> 0.047371134 | G13: ='NAV Data'!G12/'NAV Data'!G11-1 -> 0.039805699 | I13: 45536 | J13: =J12*(1+B13) -> 120.19926 | K13: =K12*(1+C13) -> 122.24653 | L13: =L12*(1+D13) -> 130.13313 | M13: =M12*(1+E13) -> 121.6504 | N13: =N12*(1+F13) -> 123.06692 | O13: =O12*(1+G13) -> 112.73106 | Q13: 45536 | R13: =MAX(R12,J13) -> 120.19926 | S13: =MAX(S12,K13) -> 122.24653 | T13: =MAX(T12,L13) -> 130.13313 | U13: =MAX(U12,M13) -> 121.6504 | V13: =MAX(V12,N13) -> 123.06692 | W13: =MAX(W12,O13) -> 113.23649 | Y13: 45536 | Z13: =J13/R13-1 -> 0 | AA13: =K13/S13-1 -> 0 | AB13: =L13/T13-1 -> 0 | AC13: =M13/U13-1 -> 0 | AD13: =N13/V13-1 -> 0 | AE13: =O13/W13-1 -> -0.0044634497 | AG13: 45536 | AH13: =B13-$G13 -> -0.022262788 | AI13: =C13-$G13 -> 0.014187982 | AJ13: =D13-$G13 -> -0.017277666 | AK13: =E13-$G13 -> -0.013577456 | AL13: =F13-$G13 -> 0.0075654351
A14: 45566 | B14: ='NAV Data'!B13/'NAV Data'!B12-1 -> 0.0024756676 | C14: ='NAV Data'!C13/'NAV Data'!C12-1 -> 0.003063439 | D14: ='NAV Data'!D13/'NAV Data'!D12-1 -> 0.008172325 | E14: ='NAV Data'!E13/'NAV Data'!E12-1 -> 0.02357886 | F14: ='NAV Data'!F13/'NAV Data'!F12-1 -> 0.0045740012 | G14: ='NAV Data'!G13/'NAV Data'!G12-1 -> 0.012854679 | I14: 45566 | J14: =J13*(1+B14) -> 120.49684 | K14: =K13*(1+C14) -> 122.62103 | L14: =L13*(1+D14) -> 131.19662 | M14: =M13*(1+E14) -> 124.51878 | N14: =N13*(1+F14) -> 123.62983 | O14: =O13*(1+G14) -> 114.18019 | Q14: 45566 | R14: =MAX(R13,J14) -> 120.49684 | S14: =MAX(S13,K14) -> 122.62103 | T14: =MAX(T13,L14) -> 131.19662 | U14: =MAX(U13,M14) -> 124.51878 | V14: =MAX(V13,N14) -> 123.62983 | W14: =MAX(W13,O14) -> 114.18019 | Y14: 45566 | Z14: =J14/R14-1 -> 0 | AA14: =K14/S14-1 -> 0 | AB14: =L14/T14-1 -> 0 | AC14: =M14/U14-1 -> 0 | AD14: =N14/V14-1 -> 0 | AE14: =O14/W14-1 -> 0 | AG14: 45566 | AH14: =B14-$G14 -> -0.010379012 | AI14: =C14-$G14 -> -0.0097912404 | AJ14: =D14-$G14 -> -0.0046823544 | AK14: =E14-$G14 -> 0.010724181 | AL14: =F14-$G14 -> -0.0082806783
A15: 45597 | B15: ='NAV Data'!B14/'NAV Data'!B13-1 -> -0.010925214 | C15: ='NAV Data'!C14/'NAV Data'!C13-1 -> -0.017928807 | D15: ='NAV Data'!D14/'NAV Data'!D13-1 -> -0.013784673 | E15: ='NAV Data'!E14/'NAV Data'!E13-1 -> -0.017393964 | F15: ='NAV Data'!F14/'NAV Data'!F13-1 -> -0.016325494 | G15: ='NAV Data'!G14/'NAV Data'!G13-1 -> -0.028873239 | I15: 45597 | J15: =J14*(1+B15) -> 119.18038 | K15: =K14*(1+C15) -> 120.42258 | L15: =L14*(1+D15) -> 129.38812 | M15: =M14*(1+E15) -> 122.35291 | N15: =N14*(1+F15) -> 121.61151 | O15: =O14*(1+G15) -> 110.88343 | Q15: 45597 | R15: =MAX(R14,J15) -> 120.49684 | S15: =MAX(S14,K15) -> 122.62103 | T15: =MAX(T14,L15) -> 131.19662 | U15: =MAX(U14,M15) -> 124.51878 | V15: =MAX(V14,N15) -> 123.62983 | W15: =MAX(W14,O15) -> 114.18019 | Y15: 45597 | Z15: =J15/R15-1 -> -0.010925214 | AA15: =K15/S15-1 -> -0.017928807 | AB15: =L15/T15-1 -> -0.013784673 | AC15: =M15/U15-1 -> -0.017393964 | AD15: =N15/V15-1 -> -0.016325494 | AE15: =O15/W15-1 -> -0.028873239 | AG15: 45597 | AH15: =B15-$G15 -> 0.017948026 | AI15: =C15-$G15 -> 0.010944432 | AJ15: =D15-$G15 -> 0.015088567 | AK15: =E15-$G15 -> 0.011479276 | AL15: =F15-$G15 -> 0.012547745
A16: 45627 | B16: ='NAV Data'!B15/'NAV Data'!B14-1 -> -0.0018053068 | C16: ='NAV Data'!C15/'NAV Data'!C14-1 -> -0.0010698218 | D16: ='NAV Data'!D15/'NAV Data'!D14-1 -> 0.0039001491 | E16: ='NAV Data'!E15/'NAV Data'!E14-1 -> 0.010865652 | F16: ='NAV Data'!F15/'NAV Data'!F14-1 -> -0.012039346 | G16: ='NAV Data'!G15/'NAV Data'!G14-1 -> -0.002932528 | I16: 45627 | J16: =J15*(1+B16) -> 118.96522 | K16: =K15*(1+C16) -> 120.29375 | L16: =L15*(1+D16) -> 129.89275 | M16: =M15*(1+E16) -> 123.68235 | N16: =N15*(1+F16) -> 120.14739 | O16: =O15*(1+G16) -> 110.55827 | Q16: 45627 | R16: =MAX(R15,J16) -> 120.49684 | S16: =MAX(S15,K16) -> 122.62103 | T16: =MAX(T15,L16) -> 131.19662 | U16: =MAX(U15,M16) -> 124.51878 | V16: =MAX(V15,N16) -> 123.62983 | W16: =MAX(W15,O16) -> 114.18019 | Y16: 45627 | Z16: =J16/R16-1 -> -0.012710797 | AA16: =K16/S16-1 -> -0.018979448 | AB16: =L16/T16-1 -> -0.0099382858 | AC16: =M16/U16-1 -> -0.0067173087 | AD16: =N16/V16-1 -> -0.028168292 | AE16: =O16/W16-1 -> -0.031721096 | AG16: 45627 | AH16: =B16-$G16 -> 0.0011272211 | AI16: =C16-$G16 -> 0.0018627061 | AJ16: =D16-$G16 -> 0.0068326771 | AK16: =E16-$G16 -> 0.01379818 | AL16: =F16-$G16 -> -0.0091068184
A17: 45658 | B17: ='NAV Data'!B16/'NAV Data'!B15-1 -> 0.02748424 | C17: ='NAV Data'!C16/'NAV Data'!C15-1 -> 0.026774819 | D17: ='NAV Data'!D16/'NAV Data'!D15-1 -> 0.027678904 | E17: ='NAV Data'!E16/'NAV Data'!E15-1 -> 0.027117006 | F17: ='NAV Data'!F16/'NAV Data'!F15-1 -> 0.024529747 | G17: ='NAV Data'!G16/'NAV Data'!G15-1 -> 0.014785687 | I17: 45658 | J17: =J16*(1+B17) -> 122.23489 | K17: =K16*(1+C17) -> 123.51459 | L17: =L16*(1+D17) -> 133.48804 | M17: =M16*(1+E17) -> 127.03625 | N17: =N16*(1+F17) -> 123.09458 | O17: =O16*(1+G17) -> 112.19295 | Q17: 45658 | R17: =MAX(R16,J17) -> 122.23489 | S17: =MAX(S16,K17) -> 123.51459 | T17: =MAX(T16,L17) -> 133.48804 | U17: =MAX(U16,M17) -> 127.03625 | V17: =MAX(V16,N17) -> 123.62983 | W17: =MAX(W16,O17) -> 114.18019 | Y17: 45658 | Z17: =J17/R17-1 -> 0 | AA17: =K17/S17-1 -> 0 | AB17: =L17/T17-1 -> 0 | AC17: =M17/U17-1 -> 0 | AD17: =N17/V17-1 -> -0.0043295061 | AE17: =O17/W17-1 -> -0.017404427 | AG17: 45658 | AH17: =B17-$G17 -> 0.012698553 | AI17: =C17-$G17 -> 0.011989132 | AJ17: =D17-$G17 -> 0.012893217 | AK17: =E17-$G17 -> 0.012331319 | AL17: =F17-$G17 -> 0.0097440597
... A35: 46204 | B35: ='NAV Data'!B34/'NAV Data'!B33-1 -> -0.017400412 | C35: ='NAV Data'!C34/'NAV Data'!C33-1 -> -0.0043984631 | D35: ='NAV Data'!D34/'NAV Data'!D33-1 -> -0.0093830519 | E35: ='NAV Data'!E34/'NAV Data'!E33-1 -> -0.0042183246 | F35: ='NAV Data'!F34/'NAV Data'!F33-1 -> 0.0012576828 | G35: ='NAV Data'!G34/'NAV Data'!G33-1 -> 0.012290327 | I35: 46204 | J35: =J34*(1+B35) -> 128.99709 | K35: =K34*(1+C35) -> 152.68554 | L35: =L34*(1+D35) -> 143.29116 | M35: =M34*(1+E35) -> 154.53747 | N35: =N34*(1+F35) -> 156.73672 | O35: =O34*(1+G35) -> 164.98869 | Q35: 46204 | R35: =MAX(R34,J35) -> 146.50658 | S35: =MAX(S34,K35) -> 170.32891 | T35: =MAX(T34,L35) -> 160.57417 | U35: =MAX(U34,M35) -> 167.38185 | V35: =MAX(V34,N35) -> 171.38133 | W35: =MAX(W34,O35) -> 164.98869 | Y35: 46204 | Z35: =J35/R35-1 -> -0.11951332 | AA35: =K35/S35-1 -> -0.10358415 | AB35: =L35/T35-1 -> -0.10763255 | AC35: =M35/U35-1 -> -0.076736977 | AD35: =N35/V35-1 -> -0.085450474 | AE35: =O35/W35-1 -> 0 | AG35: 46204 | AH35: =B35-$G35 -> -0.029690739 | AI35: =C35-$G35 -> -0.01668879 | AJ35: =D35-$G35 -> -0.021673379 | AK35: =E35-$G35 -> -0.016508652 | AL35: =F35-$G35 -> -0.011032644

Sheet Performance
A1: Fund and Benchmark Performance Summary
A3: Asset | B3: Start Value | C3: End Value | D3: Total Return | E3: CAGR | F3: Avg Monthly Return | G3: Annualized Volatility | H3: Sharpe Ratio | I3: Best Month | J3: Worst Month | K3: Positive Months | L3: Max Drawdown
A4: VESAF | B4: ='NAV Data'!B4 -> 25832.28 | C4: ='NAV Data'!B34 -> 33322.89 | D4: =C4/B4-1 -> 0.28997092 | E4: =(C4/B4)^(12/30)-1 -> 0.10721502 | F4: =AVERAGE('Monthly Returns'!B6:B35) -> 0.0095775236 | G4: =_xlfn.SINGLE(_xlfn.STDEV.S('Monthly Returns'!B6:B35))*SQRT(12) -> 0.1635687 | H4: =(E4-Inputs!$B$5)/G4 -> 0.38036017 | I4: =MAX('Monthly Returns'!B6:B35) -> 0.1333411 | J4: =MIN('Monthly Returns'!B6:B35) -> -0.082373637 | K4: =COUNTIF('Monthly Returns'!B6:B35,">0")/COUNT('Monthly Returns'!B6:B35) -> 0.53333333 | L4: =MIN('Monthly Returns'!Z5:Z35) -> -0.11951332
A5: DCDS | B5: ='NAV Data'!C4 -> 65931.49 | C5: ='NAV Data'!C34 -> 100667.85 | D5: =C5/B5-1 -> 0.52685538 | E5: =(C5/B5)^(12/30)-1 -> 0.18445662 | F5: =AVERAGE('Monthly Returns'!C6:C35) -> 0.015388792 | G5: =_xlfn.SINGLE(_xlfn.STDEV.S('Monthly Returns'!C6:C35))*SQRT(12) -> 0.17356649 | H5: =(E5-Inputs!$B$5)/G5 -> 0.80347667 | I5: =MAX('Monthly Returns'!C6:C35) -> 0.12733472 | J5: =MIN('Monthly Returns'!C6:C35) -> -0.092574478 | K5: =COUNTIF('Monthly Returns'!C6:C35,">0")/COUNT('Monthly Returns'!C6:C35) -> 0.6 | L5: =MIN('Monthly Returns'!AA5:AA35) -> -0.10358415
A6: SSISCA | B6: ='NAV Data'!D4 -> 30576.68 | C6: ='NAV Data'!D34 -> 43813.68 | D6: =C6/B6-1 -> 0.43291162 | E6: =(C6/B6)^(12/30)-1 -> 0.15474944 | F6: =AVERAGE('Monthly Returns'!D6:D35) -> 0.013024014 | G6: =_xlfn.SINGLE(_xlfn.STDEV.S('Monthly Returns'!D6:D35))*SQRT(12) -> 0.15564429 | H6: =(E6-Inputs!$B$5)/G6 -> 0.70512988 | I6: =MAX('Monthly Returns'!D6:D35) -> 0.11235701 | J6: =MIN('Monthly Returns'!D6:D35) -> -0.088567167 | K6: =COUNTIF('Monthly Returns'!D6:D35,">0")/COUNT('Monthly Returns'!D6:D35) -> 0.56666667 | L6: =MIN('Monthly Returns'!AB5:AB35) -> -0.11363749
A7: VCBF-BCF | B7: ='NAV Data'!E4 -> 28149.36 | C7: ='NAV Data'!E34 -> 43501.31 | D7: =C7/B7-1 -> 0.54537474 | E7: =(C7/B7)^(12/30)-1 -> 0.1901824 | F7: =AVERAGE('Monthly Returns'!E6:E35) -> 0.015395775 | G7: =_xlfn.SINGLE(_xlfn.STDEV.S('Monthly Returns'!E6:E35))*SQRT(12) -> 0.14092402 | H7: =(E7-Inputs!$B$5)/G7 -> 1.0302176 | I7: =MAX('Monthly Returns'!E6:E35) -> 0.10421007 | J7: =MIN('Monthly Returns'!E6:E35) -> -0.05051574 | K7: =COUNTIF('Monthly Returns'!E6:E35,">0")/COUNT('Monthly Returns'!E6:E35) -> 0.56666667 | L7: =MIN('Monthly Returns'!AC5:AC35) -> -0.076736977
A8: MAGEF | B8: ='NAV Data'!F4 -> 13886.81 | C8: ='NAV Data'!F34 -> 21765.73 | D8: =C8/B8-1 -> 0.56736716 | E8: =(C8/B8)^(12/30)-1 -> 0.19692875 | F8: =AVERAGE('Monthly Returns'!F6:F35) -> 0.016224406 | G8: =_xlfn.STDEV.S('Monthly Returns'!F6:F35)*SQRT(12) -> 0.16975178 | H8: =(E8-Inputs!$B$5)/G8 -> 0.89500531 | I8: =MAX('Monthly Returns'!F6:F35) -> 0.1487344 | J8: =MIN('Monthly Returns'!F6:F35) -> -0.083027723 | K8: =COUNTIF('Monthly Returns'!F6:F35,">0")/COUNT('Monthly Returns'!F6:F35) -> 0.6 | L8: =MIN('Monthly Returns'!AD5:AD35) -> -0.095875291
A9: VN-Index | B9: ='NAV Data'!G4 -> 1131.72 | C9: ='NAV Data'!G34 -> 1867.21 | D9: =C9/B9-1 -> 0.6498869 | E9: =(C9/B9)^(12/30)-1 -> 0.22174809 | F9: =AVERAGE('Monthly Returns'!G6:G35) -> 0.017855721 | G9: =_xlfn.STDEV.S('Monthly Returns'!G6:G35)*SQRT(12) -> 0.16111178 | H9: =(E9-Inputs!$B$5)/G9 -> 1.0970525 | I9: =MAX('Monthly Returns'!G6:G35) -> 0.12445743 | J9: =MIN('Monthly Returns'!G6:G35) -> -0.077552679 | K9: =COUNTIF('Monthly Returns'!G6:G35,">0")/COUNT('Monthly Returns'!G6:G35) -> 0.63333333 | L9: =MIN('Monthly Returns'!AE5:AE35) -> -0.077552679
A12: Interpretation
A13: Highest fund CAGR | B13: MAGEF | C13: 0.19692875
A14: Highest fund Sharpe | B14: VCBF-BCF | C14: 1.0302176
A15: VN-Index CAGR | B15: VN-Index | C15: 0.22174809
A16: Sample period | B16: Jan 2024 – Jul 2026 | C16: 30

Sheet Benchmark
A1: Benchmark Analysis versus VN-Index
A2: Beta, CAPM alpha, correlation, R-squared, tracking error and information ratio.
A4: Fund | B4: Beta | C4: CAPM Alpha | D4: Correlation | E4: R-Squared | F4: Tracking Error | G4: Information Ratio | H4: Excess CAGR
A5: VESAF | B5: =_xlfn.COVARIANCE.S('Monthly Returns'!B6:B35,'Monthly Returns'!$G$6:$G$35)/_xlfn.VAR.S('Monthly Returns'!$G$6:$G$35) -> 0.66694438 | C5: =Performance!F4*12-(Inputs!$B$5+B5*(Performance!$F$9*12-Inputs!$B$5)) -> -0.042962491 | D5: =CORREL('Monthly Returns'!B6:B35,'Monthly Returns'!$G$6:$G$35) -> 0.65692642 | E5: =D5^2 -> 0.43155232 | F5: =_xlfn.STDEV.S('Monthly Returns'!AH6:AH35)*SQRT(12) -> 0.13449151 | G5: =AVERAGE('Monthly Returns'!AH6:AH35)*12/F5 -> -0.73862183 | H5: =Performance!E4-Performance!$E$9 -> -0.11453307
A6: DCDS | B6: =_xlfn.COVARIANCE.S('Monthly Returns'!C6:C35,'Monthly Returns'!$G$6:$G$35)/_xlfn.VAR.S('Monthly Returns'!$G$6:$G$35) -> 0.94806636 | C6: =Performance!F5*12-(Inputs!$B$5+B6*(Performance!$F$9*12-Inputs!$B$5)) -> -0.020812413 | D6: =CORREL('Monthly Returns'!C6:C35,'Monthly Returns'!$G$6:$G$35) -> 0.88003545 | E6: =D6^2 -> 0.7744624 | F6: =_xlfn.STDEV.S('Monthly Returns'!AI6:AI35)*SQRT(12) -> 0.08285169 | G6: =AVERAGE('Monthly Returns'!AI6:AI35)*12/F6 -> -0.35730291 | H6: =Performance!E5-Performance!$E$9 -> -0.037291468
A7: SSISCA | B7: =_xlfn.COVARIANCE.S('Monthly Returns'!D6:D35,'Monthly Returns'!$G$6:$G$35)/_xlfn.VAR.S('Monthly Returns'!$G$6:$G$35) -> 0.67185018 | C7: =Performance!F6*12-(Inputs!$B$5+B7*(Performance!$F$9*12-Inputs!$B$5)) -> -0.0024350075 | D7: =CORREL('Monthly Returns'!D6:D35,'Monthly Returns'!$G$6:$G$35) -> 0.695451 | E7: =D7^2 -> 0.48365209 | F7: =_xlfn.STDEV.S('Monthly Returns'!AJ6:AJ35)*SQRT(12) -> 0.12370818 | G7: =AVERAGE('Monthly Returns'!AJ6:AJ35)*12/F7 -> -0.46868755 | H7: =Performance!E6-Performance!$E$9 -> -0.066998649
A8: VCBF-BCF | B8: =_xlfn.COVARIANCE.S('Monthly Returns'!E6:E35,'Monthly Returns'!$G$6:$G$35)/_xlfn.VAR.S('Monthly Returns'!$G$6:$G$35) -> 0.70406594 | C8: =Performance!F7*12-(Inputs!$B$5+B8*(Performance!$F$9*12-Inputs!$B$5)) -> 0.020573016 | D8: =CORREL('Monthly Returns'!E6:E35,'Monthly Returns'!$G$6:$G$35) -> 0.80492538 | E8: =D8^2 -> 0.64790486 | F8: =_xlfn.STDEV.S('Monthly Returns'!AK6:AK35)*SQRT(12) -> 0.096258491 | G8: =AVERAGE('Monthly Returns'!AK6:AK35)*12/F8 -> -0.30666742 | H8: =Performance!E7-Performance!$E$9 -> -0.031565691
A9: MAGEF | B9: =_xlfn.COVARIANCE.S('Monthly Returns'!F6:F35,'Monthly Returns'!$G$6:$G$35)/_xlfn.VAR.S('Monthly Returns'!$G$6:$G$35) -> 0.9387142 | C9: =Performance!F8*12-(Inputs!$B$5+B9*(Performance!$F$9*12-Inputs!$B$5)) -> -0.0092020123 | D9: =CORREL('Monthly Returns'!F6:F35,'Monthly Returns'!$G$6:$G$35) -> 0.89093567 | E9: =D9^2 -> 0.79376638 | F9: =_xlfn.STDEV.S('Monthly Returns'!AL6:AL35)*SQRT(12) -> 0.077719063 | G9: =AVERAGE('Monthly Returns'!AL6:AL35)*12/F9 -> -0.2518787 | H9: =Performance!E8-Performance!$E$9 -> -0.024819345

Sheet Correlation
A1: Fund Correlation and Annualized Covariance
A2: Correlation shows co-movement; covariance is used in portfolio volatility calculations.
A4: Correlation | B4: VESAF | C4: DCDS | D4: SSISCA | E4: VCBF-BCF | F4: MAGEF
A5: VESAF | B5: =CORREL('Monthly Returns'!B6:B35,'Monthly Returns'!B6:B35) -> 1 | C5: =CORREL('Monthly Returns'!B6:B35,'Monthly Returns'!C6:C35) -> 0.81265725 | D5: =CORREL('Monthly Returns'!B6:B35,'Monthly Returns'!D6:D35) -> 0.96225818 | E5: =CORREL('Monthly Returns'!B6:B35,'Monthly Returns'!E6:E35) -> 0.89425282 | F5: =CORREL('Monthly Returns'!B6:B35,'Monthly Returns'!F6:F35) -> 0.87824159
A6: DCDS | B6: =CORREL('Monthly Returns'!C6:C35,'Monthly Returns'!B6:B35) -> 0.81265725 | C6: =CORREL('Monthly Returns'!C6:C35,'Monthly Returns'!C6:C35) -> 1 | D6: =CORREL('Monthly Returns'!C6:C35,'Monthly Returns'!D6:D35) -> 0.81177908 | E6: =CORREL('Monthly Returns'!C6:C35,'Monthly Returns'!E6:E35) -> 0.87559063 | F6: =CORREL('Monthly Returns'!C6:C35,'Monthly Returns'!F6:F35) -> 0.95082999
A7: SSISCA | B7: =CORREL('Monthly Returns'!D6:D35,'Monthly Returns'!B6:B35) -> 0.96225818 | C7: =CORREL('Monthly Returns'!D6:D35,'Monthly Returns'!C6:C35) -> 0.81177908 | D7: =CORREL('Monthly Returns'!D6:D35,'Monthly Returns'!D6:D35) -> 1 | E7: =CORREL('Monthly Returns'!D6:D35,'Monthly Returns'!E6:E35) -> 0.91049606 | F7: =CORREL('Monthly Returns'!D6:D35,'Monthly Returns'!F6:F35) -> 0.87679587
A8: VCBF-BCF | B8: =CORREL('Monthly Returns'!E6:E35,'Monthly Returns'!B6:B35) -> 0.89425282 | C8: =CORREL('Monthly Returns'!E6:E35,'Monthly Returns'!C6:C35) -> 0.87559063 | D8: =CORREL('Monthly Returns'!E6:E35,'Monthly Returns'!D6:D35) -> 0.91049606 | E8: =CORREL('Monthly Returns'!E6:E35,'Monthly Returns'!E6:E35) -> 1 | F8: =CORREL('Monthly Returns'!E6:E35,'Monthly Returns'!F6:F35) -> 0.92846295
A9: MAGEF | B9: =CORREL('Monthly Returns'!F6:F35,'Monthly Returns'!B6:B35) -> 0.87824159 | C9: =CORREL('Monthly Returns'!F6:F35,'Monthly Returns'!C6:C35) -> 0.95082999 | D9: =CORREL('Monthly Returns'!F6:F35,'Monthly Returns'!D6:D35) -> 0.87679587 | E9: =CORREL('Monthly Returns'!F6:F35,'Monthly Returns'!E6:E35) -> 0.92846295 | F9: =CORREL('Monthly Returns'!F6:F35,'Monthly Returns'!F6:F35) -> 1
A12: Annualized Covariance | B12: VESAF | C12: DCDS | D12: SSISCA | E12: VCBF-BCF | F12: MAGEF
A13: VESAF | B13: =_xlfn.COVARIANCE.S('Monthly Returns'!B6:B35,'Monthly Returns'!B6:B35)*12 -> 0.026754719 | C13: =_xlfn.SINGLE(_xlfn.COVARIANCE.S('Monthly Returns'!B6:B35,'Monthly Returns'!C6:C35))*12 -> 0.023071375 | D13: =_xlfn.SINGLE(_xlfn.COVARIANCE.S('Monthly Returns'!B6:B35,'Monthly Returns'!D6:D35))*12 -> 0.024497683 | E13: =_xlfn.SINGLE(_xlfn.COVARIANCE.S('Monthly Returns'!B6:B35,'Monthly Returns'!E6:E35))*12 -> 0.020613205 | F13: =_xlfn.SINGLE(_xlfn.COVARIANCE.S('Monthly Returns'!B6:B35,'Monthly Returns'!F6:F35))*12 -> 0.024385325
A14: DCDS | B14: =_xlfn.SINGLE(_xlfn.COVARIANCE.S('Monthly Returns'!C6:C35,'Monthly Returns'!B6:B35))*12 -> 0.023071375 | C14: =_xlfn.SINGLE(_xlfn.COVARIANCE.S('Monthly Returns'!C6:C35,'Monthly Returns'!C6:C35))*12 -> 0.030125326 | D14: =_xlfn.SINGLE(_xlfn.COVARIANCE.S('Monthly Returns'!C6:C35,'Monthly Returns'!D6:D35))*12 -> 0.021929914 | E14: =_xlfn.SINGLE(_xlfn.COVARIANCE.S('Monthly Returns'!C6:C35,'Monthly Returns'!E6:E35))*12 -> 0.021416673 | F14: =_xlfn.SINGLE(_xlfn.COVARIANCE.S('Monthly Returns'!C6:C35,'Monthly Returns'!F6:F35))*12 -> 0.028014514
A15: SSISCA | B15: =_xlfn.SINGLE(_xlfn.COVARIANCE.S('Monthly Returns'!D6:D35,'Monthly Returns'!B6:B35))*12 -> 0.024497683 | C15: =_xlfn.SINGLE(_xlfn.COVARIANCE.S('Monthly Returns'!D6:D35,'Monthly Returns'!C6:C35))*12 -> 0.021929914 | D15: =_xlfn.SINGLE(_xlfn.COVARIANCE.S('Monthly Returns'!D6:D35,'Monthly Returns'!D6:D35))*12 -> 0.024225146 | E15: =_xlfn.SINGLE(_xlfn.COVARIANCE.S('Monthly Returns'!D6:D35,'Monthly Returns'!E6:E35))*12 -> 0.019970838 | F15: =_xlfn.SINGLE(_xlfn.COVARIANCE.S('Monthly Returns'!D6:D35,'Monthly Returns'!F6:F35))*12 -> 0.023165733
A16: VCBF-BCF | B16: =_xlfn.SINGLE(_xlfn.COVARIANCE.S('Monthly Returns'!E6:E35,'Monthly Returns'!B6:B35))*12 -> 0.020613205 | C16: =_xlfn.SINGLE(_xlfn.COVARIANCE.S('Monthly Returns'!E6:E35,'Monthly Returns'!C6:C35))*12 -> 0.021416673 | D16: =_xlfn.SINGLE(_xlfn.COVARIANCE.S('Monthly Returns'!E6:E35,'Monthly Returns'!D6:D35))*12 -> 0.019970838 | E16: =_xlfn.SINGLE(_xlfn.COVARIANCE.S('Monthly Returns'!E6:E35,'Monthly Returns'!E6:E35))*12 -> 0.019859579 | F16: =_xlfn.SINGLE(_xlfn.COVARIANCE.S('Monthly Returns'!E6:E35,'Monthly Returns'!F6:F35))*12 -> 0.022210787
A17: MAGEF | B17: =_xlfn.SINGLE(_xlfn.COVARIANCE.S('Monthly Returns'!F6:F35,'Monthly Returns'!B6:B35))*12 -> 0.024385325 | C17: =_xlfn.SINGLE(_xlfn.COVARIANCE.S('Monthly Returns'!F6:F35,'Monthly Returns'!C6:C35))*12 -> 0.028014514 | D17: =_xlfn.SINGLE(_xlfn.COVARIANCE.S('Monthly Returns'!F6:F35,'Monthly Returns'!D6:D35))*12 -> 0.023165733 | E17: =_xlfn.SINGLE(_xlfn.COVARIANCE.S('Monthly Returns'!F6:F35,'Monthly Returns'!E6:E35))*12 -> 0.022210787 | F17: =_xlfn.SINGLE(_xlfn.COVARIANCE.S('Monthly Returns'!F6:F35,'Monthly Returns'!F6:F35))*12 -> 0.028815668

Sheet Portfolio Analysis
A1: Portfolio Construction and Strategy Comparison
A3: Fund | B3: Equal Weight | C3: Manual | D3: Minimum Variance | E3: Maximum Sharpe | G3: Date | H3: Equal Weight | I3: Manual | J3: Minimum Variance | K3: Maximum Sharpe | L3: VN-Index
A4: VESAF | B4: 0.2 | C4: =Inputs!E5 -> 0.2 | D4: 0.065665451 | E4: 0 | G4: 45292
A5: DCDS | B5: 0.2 | C5: =Inputs!E6 -> 0.25 | D5: 0.13433455 | E5: 0.2 | G5: 45323 | H5: =$B$4*'Monthly Returns'!$B6+$B$5*'Monthly Returns'!$C6+$B$6*'Monthly Returns'!$D6+$B$7*'Monthly Returns'!$E6+$B$8*'Monthly Returns'!$F6 -> 0.045732608 | I5: =$C$4*'Monthly Returns'!$B6+$C$5*'Monthly Returns'!$C6+$C$6*'Monthly Returns'!$D6+$C$7*'Monthly Returns'!$E6+$C$8*'Monthly Returns'!$F6 -> 0.04343002 | J5: =$D$4*'Monthly Returns'!$B6+$D$5*'Monthly Returns'!$C6+$D$6*'Monthly Returns'!$D6+$D$7*'Monthly Returns'!$E6+$D$8*'Monthly Returns'!$F6 -> 0.051756575 | K5: =$E$4*'Monthly Returns'!$B6+$E$5*'Monthly Returns'!$C6+$E$6*'Monthly Returns'!$D6+$E$7*'Monthly Returns'!$E6+$E$8*'Monthly Returns'!$F6 -> 0.043451552 | L5: ='Monthly Returns'!G6 -> 0.036493126
A6: SSISCA | B6: 0.2 | C6: =Inputs!E7 -> 0.1 | D6: 0.4 | E6: 9.0205621e-17 | G6: 45352 | H6: =$B$4*'Monthly Returns'!$B7+$B$5*'Monthly Returns'!$C7+$B$6*'Monthly Returns'!$D7+$B$7*'Monthly Returns'!$E7+$B$8*'Monthly Returns'!$F7 -> 0.066234269 | I6: =$C$4*'Monthly Returns'!$B7+$C$5*'Monthly Returns'!$C7+$C$6*'Monthly Returns'!$D7+$C$7*'Monthly Returns'!$E7+$C$8*'Monthly Returns'!$F7 -> 0.068553377 | J6: =$D$4*'Monthly Returns'!$B7+$D$5*'Monthly Returns'!$C7+$D$6*'Monthly Returns'!$D7+$D$7*'Monthly Returns'!$E7+$D$8*'Monthly Returns'!$F7 -> 0.071614633 | K6: =$E$4*'Monthly Returns'!$B7+$E$5*'Monthly Returns'!$C7+$E$6*'Monthly Returns'!$D7+$E$7*'Monthly Returns'!$E7+$E$8*'Monthly Returns'!$F7 -> 0.079127485 | L6: ='Monthly Returns'!G7 -> 0.072684183
A7: VCBF-BCF | B7: 0.2 | C7: =Inputs!E8 -> 0.3 | D7: 0.4 | E7: 0.4 | G7: 45383 | H7: =$B$4*'Monthly Returns'!$B8+$B$5*'Monthly Returns'!$C8+$B$6*'Monthly Returns'!$D8+$B$7*'Monthly Returns'!$E8+$B$8*'Monthly Returns'!$F8 -> 0.046962379 | I7: =$C$4*'Monthly Returns'!$B8+$C$5*'Monthly Returns'!$C8+$C$6*'Monthly Returns'!$D8+$C$7*'Monthly Returns'!$E8+$C$8*'Monthly Returns'!$F8 -> 0.044210119 | J7: =$D$4*'Monthly Returns'!$B8+$D$5*'Monthly Returns'!$C8+$D$6*'Monthly Returns'!$D8+$D$7*'Monthly Returns'!$E8+$D$8*'Monthly Returns'!$F8 -> 0.042587724 | K7: =$E$4*'Monthly Returns'!$B8+$E$5*'Monthly Returns'!$C8+$E$6*'Monthly Returns'!$D8+$E$7*'Monthly Returns'!$E8+$E$8*'Monthly Returns'!$F8 -> 0.040268677 | L7: ='Monthly Returns'!G8 -> 0.018469657
A8: MAGEF | B8: 0.2 | C8: =Inputs!E9 -> 0.15 | D8: 0 | E8: 0.4 | G8: 45413 | H8: =$B$4*'Monthly Returns'!$B9+$B$5*'Monthly Returns'!$C9+$B$6*'Monthly Returns'!$D9+$B$7*'Monthly Returns'!$E9+$B$8*'Monthly Returns'!$F9 -> -0.042348078 | I8: =$C$4*'Monthly Returns'!$B9+$C$5*'Monthly Returns'!$C9+$C$6*'Monthly Returns'!$D9+$C$7*'Monthly Returns'!$E9+$C$8*'Monthly Returns'!$F9 -> -0.044101267 | J8: =$D$4*'Monthly Returns'!$B9+$D$5*'Monthly Returns'!$C9+$D$6*'Monthly Returns'!$D9+$D$7*'Monthly Returns'!$E9+$D$8*'Monthly Returns'!$F9 -> -0.040280054 | K8: =$E$4*'Monthly Returns'!$B9+$E$5*'Monthly Returns'!$C9+$E$6*'Monthly Returns'!$D9+$E$7*'Monthly Returns'!$E9+$E$8*'Monthly Returns'!$F9 -> -0.047643061 | L8: ='Monthly Returns'!G9 -> -0.050845871
A9: Total | B9: =SUM(B4:B8) -> 1 | C9: =SUM(C4:C8) -> 1 | D9: =SUM(D4:D8) -> 1 | E9: =SUM(E4:E8) -> 1 | G9: 45444 | H9: =$B$4*'Monthly Returns'!$B10+$B$5*'Monthly Returns'!$C10+$B$6*'Monthly Returns'!$D10+$B$7*'Monthly Returns'!$E10+$B$8*'Monthly Returns'!$F10 -> 0.075891577 | I9: =$C$4*'Monthly Returns'!$B10+$C$5*'Monthly Returns'!$C10+$C$6*'Monthly Returns'!$D10+$C$7*'Monthly Returns'!$E10+$C$8*'Monthly Returns'!$F10 -> 0.075593427 | J9: =$D$4*'Monthly Returns'!$B10+$D$5*'Monthly Returns'!$C10+$D$6*'Monthly Returns'!$D10+$D$7*'Monthly Returns'!$E10+$D$8*'Monthly Returns'!$F10 -> 0.07699784 | K9: =$E$4*'Monthly Returns'!$B10+$E$5*'Monthly Returns'!$C10+$E$6*'Monthly Returns'!$D10+$E$7*'Monthly Returns'!$E10+$E$8*'Monthly Returns'!$F10 -> 0.074299304 | L9: ='Monthly Returns'!G10 -> 0.052320037
G10: 45474 | H10: =$B$4*'Monthly Returns'!$B11+$B$5*'Monthly Returns'!$C11+$B$6*'Monthly Returns'!$D11+$B$7*'Monthly Returns'!$E11+$B$8*'Monthly Returns'!$F11 -> 0.0052792551 | I10: =$C$4*'Monthly Returns'!$B11+$C$5*'Monthly Returns'!$C11+$C$6*'Monthly Returns'!$D11+$C$7*'Monthly Returns'!$E11+$C$8*'Monthly Returns'!$F11 -> 0.0036594467 | J10: =$D$4*'Monthly Returns'!$B11+$D$5*'Monthly Returns'!$C11+$D$6*'Monthly Returns'!$D11+$D$7*'Monthly Returns'!$E11+$D$8*'Monthly Returns'!$F11 -> 0.0069545899 | K10: =$E$4*'Monthly Returns'!$B11+$E$5*'Monthly Returns'!$C11+$E$6*'Monthly Returns'!$D11+$E$7*'Monthly Returns'!$E11+$E$8*'Monthly Returns'!$F11 -> -0.00073588408 | L10: ='Monthly Returns'!G11 -> -0.019875
G11: 45505 | H11: =$B$4*'Monthly Returns'!$B12+$B$5*'Monthly Returns'!$C12+$B$6*'Monthly Returns'!$D12+$B$7*'Monthly Returns'!$E12+$B$8*'Monthly Returns'!$F12 -> -0.011900215 | I11: =$C$4*'Monthly Returns'!$B12+$C$5*'Monthly Returns'!$C12+$C$6*'Monthly Returns'!$D12+$C$7*'Monthly Returns'!$E12+$C$8*'Monthly Returns'!$F12 -> -0.013225294 | J11: =$D$4*'Monthly Returns'!$B12+$D$5*'Monthly Returns'!$C12+$D$6*'Monthly Returns'!$D12+$D$7*'Monthly Returns'!$E12+$D$8*'Monthly Returns'!$F12 -> -0.0055180771 | K11: =$E$4*'Monthly Returns'!$B12+$E$5*'Monthly Returns'!$C12+$E$6*'Monthly Returns'!$D12+$E$7*'Monthly Returns'!$E12+$E$8*'Monthly Returns'!$F12 -> -0.017664397 | L11: ='Monthly Returns'!G12 -> -0.021999745
A12: Metric | B12: Equal Weight | C12: Manual | D12: Minimum Variance | E12: Maximum Sharpe | G12: 45536 | H12: =$B$4*'Monthly Returns'!$B13+$B$5*'Monthly Returns'!$C13+$B$6*'Monthly Returns'!$D13+$B$7*'Monthly Returns'!$E13+$B$8*'Monthly Returns'!$F13 -> 0.0335328 | I12: =$C$4*'Monthly Returns'!$B13+$C$5*'Monthly Returns'!$C13+$C$6*'Monthly Returns'!$D13+$C$7*'Monthly Returns'!$E13+$C$8*'Monthly Returns'!$F13 -> 0.034233948 | J12: =$D$4*'Monthly Returns'!$B13+$D$5*'Monthly Returns'!$C13+$D$6*'Monthly Returns'!$D13+$D$7*'Monthly Returns'!$E13+$D$8*'Monthly Returns'!$F13 -> 0.02790769 | K12: =$E$4*'Monthly Returns'!$B13+$E$5*'Monthly Returns'!$C13+$E$6*'Monthly Returns'!$D13+$E$7*'Monthly Returns'!$E13+$E$8*'Monthly Returns'!$F13 -> 0.040238487 | L12: ='Monthly Returns'!G13 -> 0.039805699
A13: Expected Annual Return | B13: =SUMPRODUCT(B$4:B$8,Performance!$E$4:$E$8) -> 0.16670645 | C13: =SUMPRODUCT(C$4:C$8,Performance!$E$4:$E$8) -> 0.16962614 | D13: =SUMPRODUCT(D$4:D$8,Performance!$E$4:$E$8) -> 0.16979196 | E13: =SUMPRODUCT(E$4:E$8,Performance!$E$4:$E$8) -> 0.19173578 | G13: 45566 | H13: =$B$4*'Monthly Returns'!$B14+$B$5*'Monthly Returns'!$C14+$B$6*'Monthly Returns'!$D14+$B$7*'Monthly Returns'!$E14+$B$8*'Monthly Returns'!$F14 -> 0.0083728586 | I13: =$C$4*'Monthly Returns'!$B14+$C$5*'Monthly Returns'!$C14+$C$6*'Monthly Returns'!$D14+$C$7*'Monthly Returns'!$E14+$C$8*'Monthly Returns'!$F14 -> 0.0098379839 | J13: =$D$4*'Monthly Returns'!$B14+$D$5*'Monthly Returns'!$C14+$D$6*'Monthly Returns'!$D14+$D$7*'Monthly Returns'!$E14+$D$8*'Monthly Returns'!$F14 -> 0.013274566 | K13: =$E$4*'Monthly Returns'!$B14+$E$5*'Monthly Returns'!$C14+$E$6*'Monthly Returns'!$D14+$E$7*'Monthly Returns'!$E14+$E$8*'Monthly Returns'!$F14 -> 0.011873832 | L13: ='Monthly Returns'!G14 -> 0.012854679
A14: Annualized Volatility | B14: =SQRT($B$4*$B$19+$B$5*$B$20+$B$6*$B$21+$B$7*$B$22+$B$8*$B$23) -> 0.15340568 | C14: =SQRT($C$4*$C$19+$C$5*$C$20+$C$6*$C$21+$C$7*$C$22+$C$8*$C$23) -> 0.15217429 | D14: =SQRT($D$4*$D$19+$D$5*$D$20+$D$6*$D$21+$D$7*$D$22+$D$8*$D$23) -> 0.14675964 | E14: =SQRT($E$4*$E$19+$E$5*$E$20+$E$6*$E$21+$E$7*$E$22+$E$8*$E$23) -> 0.15494997 | G14: 45597 | H14: =$B$4*'Monthly Returns'!$B15+$B$5*'Monthly Returns'!$C15+$B$6*'Monthly Returns'!$D15+$B$7*'Monthly Returns'!$E15+$B$8*'Monthly Returns'!$F15 -> -0.01527163 | I14: =$C$4*'Monthly Returns'!$B15+$C$5*'Monthly Returns'!$C15+$C$6*'Monthly Returns'!$D15+$C$7*'Monthly Returns'!$E15+$C$8*'Monthly Returns'!$F15 -> -0.015712725 | J14: =$D$4*'Monthly Returns'!$B15+$D$5*'Monthly Returns'!$C15+$D$6*'Monthly Returns'!$D15+$D$7*'Monthly Returns'!$E15+$D$8*'Monthly Returns'!$F15 -> -0.015597322 | K14: =$E$4*'Monthly Returns'!$B15+$E$5*'Monthly Returns'!$C15+$E$6*'Monthly Returns'!$D15+$E$7*'Monthly Returns'!$E15+$E$8*'Monthly Returns'!$F15 -> -0.017073545 | L14: ='Monthly Returns'!G15 -> -0.028873239
A15: Sharpe Ratio | B15: =(B13-Inputs!$B$5)/B14 -> 0.79336339 | C15: =(C13-Inputs!$B$5)/C14 -> 0.81896972 | D15: =(D13-Inputs!$B$5)/D14 -> 0.85031522 | E15: =(E13-Inputs!$B$5)/E14 -> 0.94698812 | G15: 45627 | H15: =$B$4*'Monthly Returns'!$B16+$B$5*'Monthly Returns'!$C16+$B$6*'Monthly Returns'!$D16+$B$7*'Monthly Returns'!$E16+$B$8*'Monthly Returns'!$F16 -> -2.9734815e-05 | I15: =$C$4*'Monthly Returns'!$B16+$C$5*'Monthly Returns'!$C16+$C$6*'Monthly Returns'!$D16+$C$7*'Monthly Returns'!$E16+$C$8*'Monthly Returns'!$F16 -> 0.0012152917 | J15: =$D$4*'Monthly Returns'!$B16+$D$5*'Monthly Returns'!$C16+$D$6*'Monthly Returns'!$D16+$D$7*'Monthly Returns'!$E16+$D$8*'Monthly Returns'!$F16 -> 0.0056440601 | K15: =$E$4*'Monthly Returns'!$B16+$E$5*'Monthly Returns'!$C16+$E$6*'Monthly Returns'!$D16+$E$7*'Monthly Returns'!$E16+$E$8*'Monthly Returns'!$F16 -> -0.00068344217 | L15: ='Monthly Returns'!G16 -> -0.002932528
G16: 45658 | H16: =$B$4*'Monthly Returns'!$B17+$B$5*'Monthly Returns'!$C17+$B$6*'Monthly Returns'!$D17+$B$7*'Monthly Returns'!$E17+$B$8*'Monthly Returns'!$F17 -> 0.026716943 | I16: =$C$4*'Monthly Returns'!$B17+$C$5*'Monthly Returns'!$C17+$C$6*'Monthly Returns'!$D17+$C$7*'Monthly Returns'!$E17+$C$8*'Monthly Returns'!$F17 -> 0.026773007 | J16: =$D$4*'Monthly Returns'!$B17+$D$5*'Monthly Returns'!$C17+$D$6*'Monthly Returns'!$D17+$D$7*'Monthly Returns'!$E17+$D$8*'Monthly Returns'!$F17 -> 0.027319913 | K16: =$E$4*'Monthly Returns'!$B17+$E$5*'Monthly Returns'!$C17+$E$6*'Monthly Returns'!$D17+$E$7*'Monthly Returns'!$E17+$E$8*'Monthly Returns'!$F17 -> 0.026013665 | L16: ='Monthly Returns'!G17 -> 0.014785687
G17: 45689 | H17: =$B$4*'Monthly Returns'!$B18+$B$5*'Monthly Returns'!$C18+$B$6*'Monthly Returns'!$D18+$B$7*'Monthly Returns'!$E18+$B$8*'Monthly Returns'!$F18 -> -0.0074224466 | I17: =$C$4*'Monthly Returns'!$B18+$C$5*'Monthly Returns'!$C18+$C$6*'Monthly Returns'!$D18+$C$7*'Monthly Returns'!$E18+$C$8*'Monthly Returns'!$F18 -> -0.0089461183 | J17: =$D$4*'Monthly Returns'!$B18+$D$5*'Monthly Returns'!$C18+$D$6*'Monthly Returns'!$D18+$D$7*'Monthly Returns'!$E18+$D$8*'Monthly Returns'!$F18 -> -0.0087711106 | K17: =$E$4*'Monthly Returns'!$B18+$E$5*'Monthly Returns'!$C18+$E$6*'Monthly Returns'!$D18+$E$7*'Monthly Returns'!$E18+$E$8*'Monthly Returns'!$F18 -> -0.0091334022 | L17: ='Monthly Returns'!G18 -> -0.013136858
A18: Covariance contribution | B18: Equal Weight | C18: Manual | D18: Minimum Variance | E18: Maximum Sharpe | G18: 45717 | H18: =$B$4*'Monthly Returns'!$B19+$B$5*'Monthly Returns'!$C19+$B$6*'Monthly Returns'!$D19+$B$7*'Monthly Returns'!$E19+$B$8*'Monthly Returns'!$F19 -> 0.013790525 | I18: =$C$4*'Monthly Returns'!$B19+$C$5*'Monthly Returns'!$C19+$C$6*'Monthly Returns'!$D19+$C$7*'Monthly Returns'!$E19+$C$8*'Monthly Returns'!$F19 -> 0.014969334 | J18: =$D$4*'Monthly Returns'!$B19+$D$5*'Monthly Returns'!$C19+$D$6*'Monthly Returns'!$D19+$D$7*'Monthly Returns'!$E19+$D$8*'Monthly Returns'!$F19 -> 0.020966217 | K18: =$E$4*'Monthly Returns'!$B19+$E$5*'Monthly Returns'!$C19+$E$6*'Monthly Returns'!$D19+$E$7*'Monthly Returns'!$E19+$E$8*'Monthly Returns'!$F19 -> 0.014986458 | L18: ='Monthly Returns'!G19 -> 0.04496301
A19: VESAF | B19: =$B$4*Correlation!$B$13+$B$5*Correlation!$C$13+$B$6*Correlation!$D$13+$B$7*Correlation!$E$13+$B$8*Correlation!$F$13 -> 0.023864462 | C19: =$C$4*Correlation!$B$13+$C$5*Correlation!$C$13+$C$6*Correlation!$D$13+$C$7*Correlation!$E$13+$C$8*Correlation!$F$13 -> 0.023410316 | D19: =$D$4*Correlation!$B$13+$D$5*Correlation!$C$13+$D$6*Correlation!$D$13+$D$7*Correlation!$E$13+$D$8*Correlation!$F$13 -> 0.022900499 | E19: =$E$4*Correlation!$B$13+$E$5*Correlation!$C$13+$E$6*Correlation!$D$13+$E$7*Correlation!$E$13+$E$8*Correlation!$F$13 -> 0.022613687 | G19: 45748 | H19: =$B$4*'Monthly Returns'!$B20+$B$5*'Monthly Returns'!$C20+$B$6*'Monthly Returns'!$D20+$B$7*'Monthly Returns'!$E20+$B$8*'Monthly Returns'!$F20 -> -0.029464772 | I19: =$C$4*'Monthly Returns'!$B20+$C$5*'Monthly Returns'!$C20+$C$6*'Monthly Returns'!$D20+$C$7*'Monthly Returns'!$E20+$C$8*'Monthly Returns'!$F20 -> -0.029275159 | J19: =$D$4*'Monthly Returns'!$B20+$D$5*'Monthly Returns'!$C20+$D$6*'Monthly Returns'!$D20+$D$7*'Monthly Returns'!$E20+$D$8*'Monthly Returns'!$F20 -> -0.02848878 | K19: =$E$4*'Monthly Returns'!$B20+$E$5*'Monthly Returns'!$C20+$E$6*'Monthly Returns'!$D20+$E$7*'Monthly Returns'!$E20+$E$8*'Monthly Returns'!$F20 -> -0.028286583 | L19: ='Monthly Returns'!G20 -> 0.0060792595
A20: DCDS | B20: =$B$4*Correlation!$B$14+$B$5*Correlation!$C$14+$B$6*Correlation!$D$14+$B$7*Correlation!$E$14+$B$8*Correlation!$F$14 -> 0.02491156 | C20: =$C$4*Correlation!$B$14+$C$5*Correlation!$C$14+$C$6*Correlation!$D$14+$C$7*Correlation!$E$14+$C$8*Correlation!$F$14 -> 0.024965777 | D20: =$D$4*Correlation!$B$14+$D$5*Correlation!$C$14+$D$6*Correlation!$D$14+$D$7*Correlation!$E$14+$D$8*Correlation!$F$14 -> 0.022900499 | E20: =$E$4*Correlation!$B$14+$E$5*Correlation!$C$14+$E$6*Correlation!$D$14+$E$7*Correlation!$E$14+$E$8*Correlation!$F$14 -> 0.02579754 | G20: 45778 | H20: =$B$4*'Monthly Returns'!$B21+$B$5*'Monthly Returns'!$C21+$B$6*'Monthly Returns'!$D21+$B$7*'Monthly Returns'!$E21+$B$8*'Monthly Returns'!$F21 -> -0.06361655 | I20: =$C$4*'Monthly Returns'!$B21+$C$5*'Monthly Returns'!$C21+$C$6*'Monthly Returns'!$D21+$C$7*'Monthly Returns'!$E21+$C$8*'Monthly Returns'!$F21 -> -0.05776482 | J20: =$D$4*'Monthly Returns'!$B21+$D$5*'Monthly Returns'!$C21+$D$6*'Monthly Returns'!$D21+$D$7*'Monthly Returns'!$E21+$D$8*'Monthly Returns'!$F21 -> -0.063109159 | K20: =$E$4*'Monthly Returns'!$B21+$E$5*'Monthly Returns'!$C21+$E$6*'Monthly Returns'!$D21+$E$7*'Monthly Returns'!$E21+$E$8*'Monthly Returns'!$F21 -> -0.050757408 | L20: ='Monthly Returns'!G21 -> -0.058664116
A21: SSISCA | B21: =$B$4*Correlation!$B$15+$B$5*Correlation!$C$15+$B$6*Correlation!$D$15+$B$7*Correlation!$E$15+$B$8*Correlation!$F$15 -> 0.022757863 | C21: =$C$4*Correlation!$B$15+$C$5*Correlation!$C$15+$C$6*Correlation!$D$15+$C$7*Correlation!$E$15+$C$8*Correlation!$F$15 -> 0.022270641 | D21: =$D$4*Correlation!$B$15+$D$5*Correlation!$C$15+$D$6*Correlation!$D$15+$D$7*Correlation!$E$15+$D$8*Correlation!$F$15 -> 0.02223299 | E21: =$E$4*Correlation!$B$15+$E$5*Correlation!$C$15+$E$6*Correlation!$D$15+$E$7*Correlation!$E$15+$E$8*Correlation!$F$15 -> 0.021640611 | G21: 45809 | H21: =$B$4*'Monthly Returns'!$B22+$B$5*'Monthly Returns'!$C22+$B$6*'Monthly Returns'!$D22+$B$7*'Monthly Returns'!$E22+$B$8*'Monthly Returns'!$F22 -> 0.072652811 | I21: =$C$4*'Monthly Returns'!$B22+$C$5*'Monthly Returns'!$C22+$C$6*'Monthly Returns'!$D22+$C$7*'Monthly Returns'!$E22+$C$8*'Monthly Returns'!$F22 -> 0.074868396 | J21: =$D$4*'Monthly Returns'!$B22+$D$5*'Monthly Returns'!$C22+$D$6*'Monthly Returns'!$D22+$D$7*'Monthly Returns'!$E22+$D$8*'Monthly Returns'!$F22 -> 0.06968725 | K21: =$E$4*'Monthly Returns'!$B22+$E$5*'Monthly Returns'!$C22+$E$6*'Monthly Returns'!$D22+$E$7*'Monthly Returns'!$E22+$E$8*'Monthly Returns'!$F22 -> 0.072685307 | L21: ='Monthly Returns'!G22 -> 0.077617838
A22: VCBF-BCF | B22: =$B$4*Correlation!$B$16+$B$5*Correlation!$C$16+$B$6*Correlation!$D$16+$B$7*Correlation!$E$16+$B$8*Correlation!$F$16 -> 0.020814216 | C22: =$C$4*Correlation!$B$16+$C$5*Correlation!$C$16+$C$6*Correlation!$D$16+$C$7*Correlation!$E$16+$C$8*Correlation!$F$16 -> 0.020763385 | D22: =$D$4*Correlation!$B$16+$D$5*Correlation!$C$16+$D$6*Correlation!$D$16+$D$7*Correlation!$E$16+$D$8*Correlation!$F$16 -> 0.020162741 | E22: =$E$4*Correlation!$B$16+$E$5*Correlation!$C$16+$E$6*Correlation!$D$16+$E$7*Correlation!$E$16+$E$8*Correlation!$F$16 -> 0.021111481 | G22: 45839 | H22: =$B$4*'Monthly Returns'!$B23+$B$5*'Monthly Returns'!$C23+$B$6*'Monthly Returns'!$D23+$B$7*'Monthly Returns'!$E23+$B$8*'Monthly Returns'!$F23 -> 0.046975157 | I22: =$C$4*'Monthly Returns'!$B23+$C$5*'Monthly Returns'!$C23+$C$6*'Monthly Returns'!$D23+$C$7*'Monthly Returns'!$E23+$C$8*'Monthly Returns'!$F23 -> 0.046303461 | J22: =$D$4*'Monthly Returns'!$B23+$D$5*'Monthly Returns'!$C23+$D$6*'Monthly Returns'!$D23+$D$7*'Monthly Returns'!$E23+$D$8*'Monthly Returns'!$F23 -> 0.045246236 | K22: =$E$4*'Monthly Returns'!$B23+$E$5*'Monthly Returns'!$C23+$E$6*'Monthly Returns'!$D23+$E$7*'Monthly Returns'!$E23+$E$8*'Monthly Returns'!$F23 -> 0.046086951 | L22: ='Monthly Returns'!G23 -> 0.031085834
A23: MAGEF | B23: =$B$4*Correlation!$B$17+$B$5*Correlation!$C$17+$B$6*Correlation!$D$17+$B$7*Correlation!$E$17+$B$8*Correlation!$F$17 -> 0.025318405 | C23: =$C$4*Correlation!$B$17+$C$5*Correlation!$C$17+$C$6*Correlation!$D$17+$C$7*Correlation!$E$17+$C$8*Correlation!$F$17 -> 0.025182853 | D23: =$D$4*Correlation!$B$17+$D$5*Correlation!$C$17+$D$6*Correlation!$D$17+$D$7*Correlation!$E$17+$D$8*Correlation!$F$17 -> 0.023515198 | E23: =$E$4*Correlation!$B$17+$E$5*Correlation!$C$17+$E$6*Correlation!$D$17+$E$7*Correlation!$E$17+$E$8*Correlation!$F$17 -> 0.026013485 | G23: 45870 | H23: =$B$4*'Monthly Returns'!$B24+$B$5*'Monthly Returns'!$C24+$B$6*'Monthly Returns'!$D24+$B$7*'Monthly Returns'!$E24+$B$8*'Monthly Returns'!$F24 -> 0.068907747 | I23: =$C$4*'Monthly Returns'!$B24+$C$5*'Monthly Returns'!$C24+$C$6*'Monthly Returns'!$D24+$C$7*'Monthly Returns'!$E24+$C$8*'Monthly Returns'!$F24 -> 0.072056391 | J23: =$D$4*'Monthly Returns'!$B24+$D$5*'Monthly Returns'!$C24+$D$6*'Monthly Returns'!$D24+$D$7*'Monthly Returns'!$E24+$D$8*'Monthly Returns'!$F24 -> 0.057236196 | K23: =$E$4*'Monthly Returns'!$B24+$E$5*'Monthly Returns'!$C24+$E$6*'Monthly Returns'!$D24+$E$7*'Monthly Returns'!$E24+$E$8*'Monthly Returns'!$F24 -> 0.08359468 | L23: ='Monthly Returns'!G24 -> 0.085184056
G24: 45901 | H24: =$B$4*'Monthly Returns'!$B25+$B$5*'Monthly Returns'!$C25+$B$6*'Monthly Returns'!$D25+$B$7*'Monthly Returns'!$E25+$B$8*'Monthly Returns'!$F25 -> 0.12519546 | I24: =$C$4*'Monthly Returns'!$B25+$C$5*'Monthly Returns'!$C25+$C$6*'Monthly Returns'!$D25+$C$7*'Monthly Returns'!$E25+$C$8*'Monthly Returns'!$F25 -> 0.12331078 | J24: =$D$4*'Monthly Returns'!$B25+$D$5*'Monthly Returns'!$C25+$D$6*'Monthly Returns'!$D25+$D$7*'Monthly Returns'!$E25+$D$8*'Monthly Returns'!$F25 -> 0.11248819 | K24: =$E$4*'Monthly Returns'!$B25+$E$5*'Monthly Returns'!$C25+$E$6*'Monthly Returns'!$D25+$E$7*'Monthly Returns'!$E25+$E$8*'Monthly Returns'!$F25 -> 0.12664473 | L24: ='Monthly Returns'!G25 -> 0.12445743
G25: 45931 | H25: =$B$4*'Monthly Returns'!$B26+$B$5*'Monthly Returns'!$C26+$B$6*'Monthly Returns'!$D26+$B$7*'Monthly Returns'!$E26+$B$8*'Monthly Returns'!$F26 -> -0.024585983 | I25: =$C$4*'Monthly Returns'!$B26+$C$5*'Monthly Returns'!$C26+$C$6*'Monthly Returns'!$D26+$C$7*'Monthly Returns'!$E26+$C$8*'Monthly Returns'!$F26 -> -0.025320448 | J25: =$D$4*'Monthly Returns'!$B26+$D$5*'Monthly Returns'!$C26+$D$6*'Monthly Returns'!$D26+$D$7*'Monthly Returns'!$E26+$D$8*'Monthly Returns'!$F26 -> -0.022262085 | K25: =$E$4*'Monthly Returns'!$B26+$E$5*'Monthly Returns'!$C26+$E$6*'Monthly Returns'!$D26+$E$7*'Monthly Returns'!$E26+$E$8*'Monthly Returns'!$F26 -> -0.017035411 | L25: ='Monthly Returns'!G26 -> -0.0096651401
G26: 45962 | H26: =$B$4*'Monthly Returns'!$B27+$B$5*'Monthly Returns'!$C27+$B$6*'Monthly Returns'!$D27+$B$7*'Monthly Returns'!$E27+$B$8*'Monthly Returns'!$F27 -> -0.0221858 | I26: =$C$4*'Monthly Returns'!$B27+$C$5*'Monthly Returns'!$C27+$C$6*'Monthly Returns'!$D27+$C$7*'Monthly Returns'!$E27+$C$8*'Monthly Returns'!$F27 -> -0.022692264 | J26: =$D$4*'Monthly Returns'!$B27+$D$5*'Monthly Returns'!$C27+$D$6*'Monthly Returns'!$D27+$D$7*'Monthly Returns'!$E27+$D$8*'Monthly Returns'!$F27 -> -0.015860218 | K26: =$E$4*'Monthly Returns'!$B27+$E$5*'Monthly Returns'!$C27+$E$6*'Monthly Returns'!$D27+$E$7*'Monthly Returns'!$E27+$E$8*'Monthly Returns'!$F27 -> -0.024399121 | L26: ='Monthly Returns'!G27 -> -0.028857992
G27: 45992 | H27: =$B$4*'Monthly Returns'!$B28+$B$5*'Monthly Returns'!$C28+$B$6*'Monthly Returns'!$D28+$B$7*'Monthly Returns'!$E28+$B$8*'Monthly Returns'!$F28 -> 0.0011695698 | I27: =$C$4*'Monthly Returns'!$B28+$C$5*'Monthly Returns'!$C28+$C$6*'Monthly Returns'!$D28+$C$7*'Monthly Returns'!$E28+$C$8*'Monthly Returns'!$F28 -> 0.00086426465 | J27: =$D$4*'Monthly Returns'!$B28+$D$5*'Monthly Returns'!$C28+$D$6*'Monthly Returns'!$D28+$D$7*'Monthly Returns'!$E28+$D$8*'Monthly Returns'!$F28 -> -0.00026214071 | K27: =$E$4*'Monthly Returns'!$B28+$E$5*'Monthly Returns'!$C28+$E$6*'Monthly Returns'!$D28+$E$7*'Monthly Returns'!$E28+$E$8*'Monthly Returns'!$F28 -> 0.01062969 | L27: ='Monthly Returns'!G28 -> 0.0523624
G28: 46023 | H28: =$B$4*'Monthly Returns'!$B29+$B$5*'Monthly Returns'!$C29+$B$6*'Monthly Returns'!$D29+$B$7*'Monthly Returns'!$E29+$B$8*'Monthly Returns'!$F29 -> 0.017989264 | I28: =$C$4*'Monthly Returns'!$B29+$C$5*'Monthly Returns'!$C29+$C$6*'Monthly Returns'!$D29+$C$7*'Monthly Returns'!$E29+$C$8*'Monthly Returns'!$F29 -> 0.023036682 | J28: =$D$4*'Monthly Returns'!$B29+$D$5*'Monthly Returns'!$C29+$D$6*'Monthly Returns'!$D29+$D$7*'Monthly Returns'!$E29+$D$8*'Monthly Returns'!$F29 -> 0.0091926141 | K28: =$E$4*'Monthly Returns'!$B29+$E$5*'Monthly Returns'!$C29+$E$6*'Monthly Returns'!$D29+$E$7*'Monthly Returns'!$E29+$E$8*'Monthly Returns'!$F29 -> 0.038651136 | L28: ='Monthly Returns'!G29 -> 0.050967579
G29: 46054 | H29: =$B$4*'Monthly Returns'!$B30+$B$5*'Monthly Returns'!$C30+$B$6*'Monthly Returns'!$D30+$B$7*'Monthly Returns'!$E30+$B$8*'Monthly Returns'!$F30 -> 0.064576402 | I29: =$C$4*'Monthly Returns'!$B30+$C$5*'Monthly Returns'!$C30+$C$6*'Monthly Returns'!$D30+$C$7*'Monthly Returns'!$E30+$C$8*'Monthly Returns'!$F30 -> 0.061329279 | J29: =$D$4*'Monthly Returns'!$B30+$D$5*'Monthly Returns'!$C30+$D$6*'Monthly Returns'!$D30+$D$7*'Monthly Returns'!$E30+$D$8*'Monthly Returns'!$F30 -> 0.073451036 | K29: =$E$4*'Monthly Returns'!$B30+$E$5*'Monthly Returns'!$C30+$E$6*'Monthly Returns'!$D30+$E$7*'Monthly Returns'!$E30+$E$8*'Monthly Returns'!$F30 -> 0.05141008 | L29: ='Monthly Returns'!G30 -> 0.010120778
G30: 46082 | H30: =$B$4*'Monthly Returns'!$B31+$B$5*'Monthly Returns'!$C31+$B$6*'Monthly Returns'!$D31+$B$7*'Monthly Returns'!$E31+$B$8*'Monthly Returns'!$F31 -> 0.013461662 | I30: =$C$4*'Monthly Returns'!$B31+$C$5*'Monthly Returns'!$C31+$C$6*'Monthly Returns'!$D31+$C$7*'Monthly Returns'!$E31+$C$8*'Monthly Returns'!$F31 -> 0.012027478 | J30: =$D$4*'Monthly Returns'!$B31+$D$5*'Monthly Returns'!$C31+$D$6*'Monthly Returns'!$D31+$D$7*'Monthly Returns'!$E31+$D$8*'Monthly Returns'!$F31 -> 0.0040967942 | K30: =$E$4*'Monthly Returns'!$B31+$E$5*'Monthly Returns'!$C31+$E$6*'Monthly Returns'!$D31+$E$7*'Monthly Returns'!$E31+$E$8*'Monthly Returns'!$F31 -> 0.0079233507 | L30: ='Monthly Returns'!G31 -> 0.021920841
G31: 46113 | H31: =$B$4*'Monthly Returns'!$B32+$B$5*'Monthly Returns'!$C32+$B$6*'Monthly Returns'!$D32+$B$7*'Monthly Returns'!$E32+$B$8*'Monthly Returns'!$F32 -> -0.069449866 | I31: =$C$4*'Monthly Returns'!$B32+$C$5*'Monthly Returns'!$C32+$C$6*'Monthly Returns'!$D32+$C$7*'Monthly Returns'!$E32+$C$8*'Monthly Returns'!$F32 -> -0.068055062 | J31: =$D$4*'Monthly Returns'!$B32+$D$5*'Monthly Returns'!$C32+$D$6*'Monthly Returns'!$D32+$D$7*'Monthly Returns'!$E32+$D$8*'Monthly Returns'!$F32 -> -0.06203377 | K31: =$E$4*'Monthly Returns'!$B32+$E$5*'Monthly Returns'!$C32+$E$6*'Monthly Returns'!$D32+$E$7*'Monthly Returns'!$E32+$E$8*'Monthly Returns'!$F32 -> -0.070908758 | L31: ='Monthly Returns'!G32 -> -0.077552679
G32: 46143 | H32: =$B$4*'Monthly Returns'!$B33+$B$5*'Monthly Returns'!$C33+$B$6*'Monthly Returns'!$D33+$B$7*'Monthly Returns'!$E33+$B$8*'Monthly Returns'!$F33 -> -0.0020833877 | I32: =$C$4*'Monthly Returns'!$B33+$C$5*'Monthly Returns'!$C33+$C$6*'Monthly Returns'!$D33+$C$7*'Monthly Returns'!$E33+$C$8*'Monthly Returns'!$F33 -> -0.00091035099 | J32: =$D$4*'Monthly Returns'!$B33+$D$5*'Monthly Returns'!$C33+$D$6*'Monthly Returns'!$D33+$D$7*'Monthly Returns'!$E33+$D$8*'Monthly Returns'!$F33 -> -0.0037932877 | K32: =$E$4*'Monthly Returns'!$B33+$E$5*'Monthly Returns'!$C33+$E$6*'Monthly Returns'!$D33+$E$7*'Monthly Returns'!$E33+$E$8*'Monthly Returns'!$F33 -> 0.01002392 | L32: ='Monthly Returns'!G33 -> 0.088747042
G33: 46174 | H33: =$B$4*'Monthly Returns'!$B34+$B$5*'Monthly Returns'!$C34+$B$6*'Monthly Returns'!$D34+$B$7*'Monthly Returns'!$E34+$B$8*'Monthly Returns'!$F34 -> -0.020591248 | I33: =$C$4*'Monthly Returns'!$B34+$C$5*'Monthly Returns'!$C34+$C$6*'Monthly Returns'!$D34+$C$7*'Monthly Returns'!$E34+$C$8*'Monthly Returns'!$F34 -> -0.020149404 | J33: =$D$4*'Monthly Returns'!$B34+$D$5*'Monthly Returns'!$C34+$D$6*'Monthly Returns'!$D34+$D$7*'Monthly Returns'!$E34+$D$8*'Monthly Returns'!$F34 -> -0.021349862 | K33: =$E$4*'Monthly Returns'!$B34+$E$5*'Monthly Returns'!$C34+$E$6*'Monthly Returns'!$D34+$E$7*'Monthly Returns'!$E34+$E$8*'Monthly Returns'!$F34 -> -0.019749417 | L33: ='Monthly Returns'!G34 -> -0.0051346774
G34: 46204 | H34: =$B$4*'Monthly Returns'!$B35+$B$5*'Monthly Returns'!$C35+$B$6*'Monthly Returns'!$D35+$B$7*'Monthly Returns'!$E35+$B$8*'Monthly Returns'!$F35 -> -0.0068285138 | I34: =$C$4*'Monthly Returns'!$B35+$C$5*'Monthly Returns'!$C35+$C$6*'Monthly Returns'!$D35+$C$7*'Monthly Returns'!$E35+$C$8*'Monthly Returns'!$F35 -> -0.0065948483 | J34: =$D$4*'Monthly Returns'!$B35+$D$5*'Monthly Returns'!$C35+$D$6*'Monthly Returns'!$D35+$D$7*'Monthly Returns'!$E35+$D$8*'Monthly Returns'!$F35 -> -0.0071740221 | K34: =$E$4*'Monthly Returns'!$B35+$E$5*'Monthly Returns'!$C35+$E$6*'Monthly Returns'!$D35+$E$7*'Monthly Returns'!$E35+$E$8*'Monthly Returns'!$F35 -> -0.0020639493 | L34: ='Monthly Returns'!G35 -> 0.012290327
G37: Date | H37: Equal Weight | I37: Manual | J37: Minimum Variance | K37: Maximum Sharpe | L37: VN-Index
G38: 45292 | H38: 100 | I38: 100 | J38: 100 | K38: 100 | L38: 100
G39: 45323 | H39: =H38*(1+H5) -> 104.57326 | I39: =I38*(1+I5) -> 104.343 | J39: =J38*(1+J5) -> 105.17566 | K39: =K38*(1+K5) -> 104.34516 | L39: =L38*(1+L5) -> 103.64931
G40: 45352 | H40: =H39*(1+H6) -> 111.49959 | I40: =I39*(1+I6) -> 111.49607 | J40: =J39*(1+J6) -> 112.70777 | K40: =K39*(1+K6) -> 112.60172 | L40: =L39*(1+L6) -> 111.18298
G41: 45383 | H41: =H40*(1+H7) -> 116.73588 | I41: =I40*(1+I7) -> 116.42532 | J41: =J40*(1+J7) -> 117.50774 | K41: =K40*(1+K7) -> 117.13605 | L41: =L40*(1+L7) -> 113.23649
G42: 45413 | H42: =H41*(1+H8) -> 111.79234 | I42: =I41*(1+I8) -> 111.29082 | J42: =J41*(1+J8) -> 112.77452 | K42: =K41*(1+K8) -> 111.55533 | L42: =L41*(1+L8) -> 107.47888
G43: 45444 | H43: =H42*(1+H9) -> 120.27644 | I43: =I42*(1+I9) -> 119.70367 | J43: =J42*(1+J9) -> 121.45792 | K43: =K42*(1+K9) -> 119.84381 | L43: =L42*(1+L9) -> 113.10218
G44: 45474 | H44: =H43*(1+H10) -> 120.91141 | I44: =I43*(1+I10) -> 120.14172 | J44: =J43*(1+J10) -> 122.30261 | K44: =K43*(1+K10) -> 119.75562 | L44: =L43*(1+L10) -> 110.85427
G45: 45505 | H45: =H44*(1+H11) -> 119.47254 | I45: =I44*(1+I11) -> 118.55281 | J45: =J44*(1+J11) -> 121.62773 | K45: =K44*(1+K11) -> 117.64021 | L45: =L44*(1+L11) -> 108.41551
G46: 45536 | H46: =H45*(1+H12) -> 123.47878 | I46: =I45*(1+I12) -> 122.61134 | J46: =J45*(1+J12) -> 125.02208 | K46: =K45*(1+K12) -> 122.37387 | L46: =L45*(1+L12) -> 112.73106
G47: 45566 | H47: =H46*(1+H13) -> 124.51265 | I47: =I46*(1+I13) -> 123.81759 | J47: =J46*(1+J13) -> 126.6817 | K47: =K46*(1+K13) -> 123.82692 | L47: =L46*(1+L13) -> 114.18019
G48: 45597 | H48: =H47*(1+H14) -> 122.61114 | I48: =I47*(1+I14) -> 121.87208 | J48: =J47*(1+J14) -> 124.7058 | K48: =K47*(1+K14) -> 121.71276 | L48: =L47*(1+L14) -> 110.88343
G49: 45627 | H49: =H48*(1+H15) -> 122.6075 | I49: =I48*(1+I15) -> 122.02019 | J49: =J48*(1+J15) -> 125.40965 | K49: =K48*(1+K15) -> 121.62957 | L49: =L48*(1+L15) -> 110.55827
G50: 45658 | H50: =H49*(1+H16) -> 125.8832 | I50: =I49*(1+I16) -> 125.28704 | J50: =J49*(1+J16) -> 128.83583 | K50: =K49*(1+K16) -> 124.7936 | L50: =L49*(1+L16) -> 112.19295
... G68: 46204 | H68: =H67*(1+H34) -> 147.30307 | I68: =I67*(1+I34) -> 148.22631 | J68: =J67*(1+J34) -> 148.26416 | K68: =K67*(1+K34) -> 155.3025 | L68: =L67*(1+L34) -> 164.98869

Sheet Efficient Frontier
A1: Efficient Frontier
A3: Annualized Volatility | B3: Expected Return | C3: Sharpe | D3: VESAF | E3: DCDS | F3: SSISCA | G3: VCBF-BCF | H3: MAGEF | J3: Portfolio | K3: Return | L3: Volatility
A4: 0.14675964 | B4: 0.16979196 | C4: 0.85031522 | D4: 0.065665451 | E4: 0.13433455 | F4: 0.4 | G4: 0.4 | H4: 0 | J4: Minimum Variance | K4: 0.16979196 | L4: 0.14675964
A5: 0.14676117 | B5: 0.17029068 | C5: 0.85370459 | D5: 0.059208784 | E5: 0.14079122 | F5: 0.4 | G5: 0.4 | H5: 4.7433845e-18 | J5: Maximum Sharpe | K5: 0.19173578 | L5: 0.15494997
A6: 0.14676574 | B6: 0.1707894 | C6: 0.85707606 | D6: 0.052752117 | E6: 0.14724788 | F6: 0.4 | G6: 0.4 | H6: 2.005774e-18 | J6: VN-Index | K6: 0.22174809 | L6: 0.16111178
A7: 0.14677337 | B7: 0.17128813 | C7: 0.86042946 | D7: 0.04629545 | E7: 0.15370455 | F7: 0.4 | G7: 0.4 | H7: 1.1926224e-18
A8: 0.14678404 | B8: 0.17178685 | C8: 0.86376455 | D8: 0.039838783 | E8: 0.16016122 | F8: 0.4 | G8: 0.4 | H8: 2.3852448e-18
A9: 0.14679776 | B9: 0.17228557 | C9: 0.86708116 | D9: 0.033382116 | E9: 0.16661788 | F9: 0.4 | G9: 0.4 | H9: 5.6378513e-18
A10: 0.14681453 | B10: 0.1727843 | C10: 0.87037908 | D10: 0.026925449 | E10: 0.17307455 | F10: 0.4 | G10: 0.4 | H10: 0
A11: 0.14683435 | B11: 0.17328302 | C11: 0.87365812 | D11: 0.020468782 | E11: 0.17953122 | F11: 0.4 | G11: 0.4 | H11: 9.8278982e-18
A12: 0.14685721 | B12: 0.17378174 | C12: 0.87691809 | D12: 0.014012115 | E12: 0.18598788 | F12: 0.4 | G12: 0.4 | H12: 1.7347235e-18
A13: 0.14688312 | B13: 0.17428047 | C13: 0.8801588 | D13: 0.0075554481 | E13: 0.19244455 | F13: 0.4 | G13: 0.4 | H13: 4.9431789e-18
A14: 0.14691206 | B14: 0.17477919 | C14: 0.88338008 | D14: 0.0010987811 | E14: 0.19890122 | F14: 0.4 | G14: 0.4 | H14: 0
A15: 0.14701621 | B15: 0.17527791 | C15: 0.88614658 | D15: 9.7892216e-18 | E15: 0.16681786 | F15: 0.4 | G15: 0.4 | H15: 0.033182139
A16: 0.14715277 | B16: 0.17577664 | C16: 0.88871342 | D16: 0 | E16: 0.15686986 | F16: 0.39111767 | G16: 0.4 | H16: 0.052012473
A17: 0.14729415 | B17: 0.17627536 | C17: 0.89124626 | D17: 5.5410532e-18 | E17: 0.14925547 | F17: 0.3815453 | G17: 0.4 | H17: 0.069199232
A18: 0.14744029 | B18: 0.17677408 | C18: 0.89374545 | D18: 0 | E18: 0.14164113 | F18: 0.37197292 | G18: 0.4 | H18: 0.086385951
... A48: 0.15494997 | B48: 0.19173578 | C48: 0.94698812 | D48: 0 | E48: 0.2 | F48: 0 | G48: 0.4 | H48: 0.4

Sheet Monte Carlo
A1: 10-Year Monte Carlo Simulation
A2: Maximum-Sharpe portfolio; 5,000 paths; initial investment and monthly DCA from Inputs.
A4: Parameter | B4: Value | D4: Outcome | E4: Value | F4: Terminal Value Bin | G4: Frequency | N4: Terminal Value
A5: Expected annual return | B5: 0.19173578 | D5: Mean terminal value | E5: =AVERAGE(N5:N5004) -> 2.2028274e+09 | F5: 7.3410803e+08 | G5: 38 | N5: 1.5605711e+09
A6: Annualized volatility | B6: 0.15494997 | D6: Median terminal value | E6: =MEDIAN(N5:N5004) -> 2.0481464e+09 | F6: 9.9665184e+08 | G6: 200 | N6: 3.1405366e+09
A7: Sharpe ratio | B7: 0.94698812 | D7: 10th percentile | E7: =_xludf.PERCENTILE.INC(N5:N5004,0.1) -> #NAME? | F7: 1.2591956e+09 | G7: 430 | N7: 1.7311161e+09
A8: Initial investment | B8: 100000000 | D8: 90th percentile | E8: =_xludf.PERCENTILE.INC(N5:N5004,0.9) -> #NAME? | F8: 1.5217394e+09 | G8: 717 | N8: 2.880287e+09
A9: Monthly DCA | B9: 5000000 | D9: Probability below contributions | E9: =COUNTIF(N5:N5004,"<"&$B$12)/COUNT(N5:N5004) -> 0.0012 | F9: 1.7842832e+09 | G9: 775 | N9: 3.4174722e+09
A10: Horizon (months) | B10: 120 | D10: Probability above 2× contributions | E10: =COUNTIF(N5:N5004,">"&2*$B$12)/COUNT(N5:N5004) -> 0.8614 | F10: 2.046827e+09 | G10: 683 | N10: 1.0270737e+09
A11: Simulations | B11: 5000 | F11: 2.3093709e+09 | G11: 577 | N11: 1.7520051e+09
A12: Total contributions | B12: 700000000 | F12: 2.5719147e+09 | G12: 481 | N12: 3.0567285e+09
F13: 2.8344585e+09 | G13: 319 | N13: 3.2516448e+09
F14: 3.0970023e+09 | G14: 212 | N14: 1.3592927e+09
A15: Month | B15: P10 | C15: Median | D15: P90 | F15: 3.3595461e+09 | G15: 163 | N15: 2.8168594e+09
A16: 0 | B16: 100000000 | C16: 100000000 | D16: 100000000 | F16: 3.6220899e+09 | G16: 138 | N16: 1.263828e+09
A17: 1 | B17: 1.0073817e+08 | C17: 1.0632896e+08 | D17: 1.123925e+08 | F17: 3.8846337e+09 | G17: 88 | N17: 3.4417277e+09
A18: 2 | B18: 1.0457565e+08 | C18: 1.1263139e+08 | D18: 1.2168566e+08 | F18: 4.1471775e+09 | G18: 49 | N18: 2.4257822e+09
A19: 3 | B19: 1.0874911e+08 | C19: 1.1919849e+08 | D19: 1.3041225e+08 | F19: 4.4097213e+09 | G19: 42 | N19: 4.4285781e+09
A20: 4 | B20: 1.136169e+08 | C20: 1.2598812e+08 | D20: 1.3939991e+08 | F20: 4.6722651e+09 | G20: 30 | N20: 3.6549613e+09
A21: 5 | B21: 1.1862654e+08 | C21: 1.3280579e+08 | D21: 1.4869805e+08 | F21: 4.9348089e+09 | G21: 19 | N21: 1.723166e+09
A22: 6 | B22: 1.2374178e+08 | C22: 1.3969574e+08 | D22: 1.5787265e+08 | F22: 5.1973527e+09 | G22: 12 | N22: 2.6394925e+09
A23: 7 | B23: 1.2894612e+08 | C23: 1.4649065e+08 | D23: 1.673398e+08 | F23: 5.4598965e+09 | G23: 7 | N23: 2.9874243e+09
A24: 8 | B24: 1.3394383e+08 | C24: 1.5342979e+08 | D24: 1.7678586e+08 | F24: 5.7224403e+09 | G24: 6 | N24: 1.8200034e+09
A25: 9 | B25: 1.3904897e+08 | C25: 1.6069738e+08 | D25: 1.8593059e+08 | F25: 5.9849841e+09 | G25: 7 | N25: 3.9621364e+09
A26: 10 | B26: 1.4408376e+08 | C26: 1.678291e+08 | D26: 1.9565526e+08 | F26: 6.2475279e+09 | G26: 1 | N26: 2.3109153e+09
A27: 11 | B27: 1.495773e+08 | C27: 1.7534602e+08 | D27: 2.0546414e+08 | F27: 6.5100717e+09 | G27: 2 | N27: 1.1255372e+09
... A34: 18 | B34: 1.9041114e+08 | C34: 2.2958064e+08 | D34: 2.7838616e+08 | F34: 8.3478783e+09 | G34: 2 | N34: 2.9820152e+09
A35: 19 | B35: 1.9583798e+08 | C35: 2.3809338e+08 | D35: 2.8994267e+08 | N35: 2.077425e+09
A36: 20 | B36: 2.0275519e+08 | C36: 2.4581917e+08 | D36: 3.0187582e+08 | N36: 1.6800832e+09
A37: 21 | B37: 2.0847175e+08 | C37: 2.5461926e+08 | D37: 3.1265312e+08 | N37: 1.0024952e+09
A38: 22 | B38: 2.1472567e+08 | C38: 2.6299183e+08 | D38: 3.2384026e+08 | N38: 1.6642516e+09
A39: 23 | B39: 2.2076897e+08 | C39: 2.7160574e+08 | D39: 3.3531393e+08 | N39: 1.4440715e+09
A40: 24 | B40: 2.2707403e+08 | C40: 2.8020648e+08 | D40: 3.4986159e+08 | N40: 2.6133458e+09
A41: 25 | B41: 2.3348144e+08 | C41: 2.8933555e+08 | D41: 3.6215977e+08 | N41: 2.6722889e+09
A42: 26 | B42: 2.4025237e+08 | C42: 2.9947673e+08 | D42: 3.7388274e+08 | N42: 2.0861994e+09
A43: 27 | B43: 2.4716651e+08 | C43: 3.0744746e+08 | D43: 3.8738734e+08 | N43: 1.2806077e+09
A44: 28 | B44: 2.524243e+08 | C44: 3.1603928e+08 | D44: 4.0074409e+08 | N44: 2.4132811e+09
A45: 29 | B45: 2.5907349e+08 | C45: 3.2532042e+08 | D45: 4.1517683e+08 | N45: 2.4358149e+09
A46: 30 | B46: 2.6641421e+08 | C46: 3.3499851e+08 | D46: 4.3049169e+08 | N46: 2.2761301e+09
... A136: 120 | B136: 1.301613e+09 | C136: 2.0481464e+09 | D136: 3.3263578e+09 | N136: 5.9942061e+09
N137: 9.5764734e+08
N138: 6.0031961e+09
N139: 1.5933234e+09
N140: 2.1999857e+09
N141: 1.6388982e+09
N142: 2.851758e+09
N143: 2.2276599e+09
N144: 2.1221435e+09
N145: 4.2188813e+09
N146: 1.6930021e+09
N147: 1.4953941e+09
N148: 1.6641026e+09
... N5004: 1.211368e+09

Sheet DCA Analysis
A1: DCA Analysis: Actual from Jan-2026 and Projected Thereafter
A3: Date | B3: Status | C3: Portfolio Index (Base=100) | D3: Contribution (VND) | E3: Units Purchased | F3: Cumulative Units | G3: Portfolio Value (VND) | H3: VN-Index (Base=100) | I3: VN Contribution (VND) | J3: VN Units Purchased | K3: VN Cumulative Units | L3: VN Value (VND) | M3: Cumulative Contributions (VND)
A4: 46023 | B4: Actual | C4: 100 | D4: =Inputs!$B$6 -> 10000000 | E4: =D4/C4 -> 100000 | F4: =E4 -> 100000 | G4: =F4*C4 -> 10000000 | H4: 100 | I4: =D4 -> 10000000 | J4: =I4/H4 -> 100000 | K4: =J4 -> 100000 | L4: =K4*H4 -> 10000000 | M4: =D4 -> 10000000
A5: 46054 | B5: Actual | C5: =C4*(1+'Monthly Returns'!B30*'Portfolio Analysis'!$E$4+'Monthly Returns'!C30*'Portfolio Analysis'!$E$5+'Monthly Returns'!D30*'Portfolio Analysis'!$E$6+'Monthly Returns'!E30*'Portfolio Analysis'!$E$7+'Monthly Returns'!F30*'Portfolio Analysis'!$E$8) -> 105.14101 | D5: =Inputs!$B$7 -> 10000000 | E5: =D5/C5 -> 95110.368 | F5: =F4+E5 -> 195110.37 | G5: =F5*C5 -> 20514101 | H5: =H4*(1+'Monthly Returns'!G30) -> 101.01208 | I5: =D5 -> 10000000 | J5: =I5/H5 -> 98998.063 | K5: =K4+J5 -> 198998.06 | L5: =K5*H5 -> 20101208 | M5: =M4+D5 -> 20000000
A6: 46082 | B6: Actual | C6: =C5*(1+'Monthly Returns'!B31*'Portfolio Analysis'!$E$4+'Monthly Returns'!C31*'Portfolio Analysis'!$E$5+'Monthly Returns'!D31*'Portfolio Analysis'!$E$6+'Monthly Returns'!E31*'Portfolio Analysis'!$E$7+'Monthly Returns'!F31*'Portfolio Analysis'!$E$8) -> 105.97408 | D6: =Inputs!$B$7 -> 10000000 | E6: =D6/C6 -> 94362.7 | F6: =F5+E6 -> 289473.07 | G6: =F6*C6 -> 30676641 | H6: =H5*(1+'Monthly Returns'!G31) -> 103.22635 | I6: =D6 -> 10000000 | J6: =I6/H6 -> 96874.492 | K6: =K5+J6 -> 295872.55 | L6: =K6*H6 -> 30541843 | M6: =M5+D6 -> 30000000
A7: 46113 | B7: Actual | C7: =C6*(1+'Monthly Returns'!B32*'Portfolio Analysis'!$E$4+'Monthly Returns'!C32*'Portfolio Analysis'!$E$5+'Monthly Returns'!D32*'Portfolio Analysis'!$E$6+'Monthly Returns'!E32*'Portfolio Analysis'!$E$7+'Monthly Returns'!F32*'Portfolio Analysis'!$E$8) -> 98.459587 | D7: =Inputs!$B$7 -> 10000000 | E7: =D7/C7 -> 101564.51 | F7: =F6+E7 -> 391037.58 | G7: =F7*C7 -> 38501399 | H7: =H6*(1+'Monthly Returns'!G32) -> 95.220868 | I7: =D7 -> 10000000 | J7: =I7/H7 -> 105019 | K7: =K6+J7 -> 400891.55 | L7: =K7*H7 -> 38173241 | M7: =M6+D7 -> 40000000
A8: 46143 | B8: Actual | C8: =C7*(1+'Monthly Returns'!B33*'Portfolio Analysis'!$E$4+'Monthly Returns'!C33*'Portfolio Analysis'!$E$5+'Monthly Returns'!D33*'Portfolio Analysis'!$E$6+'Monthly Returns'!E33*'Portfolio Analysis'!$E$7+'Monthly Returns'!F33*'Portfolio Analysis'!$E$8) -> 99.446538 | D8: =Inputs!$B$7 -> 10000000 | E8: =D8/C8 -> 100556.54 | F8: =F7+E8 -> 491594.12 | G8: =F8*C8 -> 48887334 | H8: =H7*(1+'Monthly Returns'!G33) -> 103.67144 | I8: =D8 -> 10000000 | J8: =I8/H8 -> 96458.583 | K8: =K7+J8 -> 497350.13 | L8: =K8*H8 -> 51561004 | M8: =M7+D8 -> 50000000
A9: 46174 | B9: Actual | C9: =C8*(1+'Monthly Returns'!B34*'Portfolio Analysis'!$E$4+'Monthly Returns'!C34*'Portfolio Analysis'!$E$5+'Monthly Returns'!D34*'Portfolio Analysis'!$E$6+'Monthly Returns'!E34*'Portfolio Analysis'!$E$7+'Monthly Returns'!F34*'Portfolio Analysis'!$E$8) -> 97.482527 | D9: =Inputs!$B$7 -> 10000000 | E9: =D9/C9 -> 102582.49 | F9: =F8+E9 -> 594176.61 | G9: =F9*C9 -> 57921837 | H9: =H8*(1+'Monthly Returns'!G34) -> 103.13912 | I9: =D9 -> 10000000 | J9: =I9/H9 -> 96956.423 | K9: =K8+J9 -> 594306.56 | L9: =K9*H9 -> 61296255 | M9: =M8+D9 -> 60000000
A10: 46204 | B10: Actual | C10: =C9*(1+'Monthly Returns'!B35*'Portfolio Analysis'!$E$4+'Monthly Returns'!C35*'Portfolio Analysis'!$E$5+'Monthly Returns'!D35*'Portfolio Analysis'!$E$6+'Monthly Returns'!E35*'Portfolio Analysis'!$E$7+'Monthly Returns'!F35*'Portfolio Analysis'!$E$8) -> 97.281328 | D10: =Inputs!$B$7 -> 10000000 | E10: =D10/C10 -> 102794.65 | F10: =F9+E10 -> 696971.26 | G10: =F10*C10 -> 67802290 | H10: =H9*(1+'Monthly Returns'!G35) -> 104.40673 | I10: =D10 -> 10000000 | J10: =I10/H10 -> 95779.264 | K10: =K9+J10 -> 690085.82 | L10: =K10*H10 -> 72049606 | M10: =M9+D10 -> 70000000
A11: 46235 | B11: Projected | C11: =C10*(1+((1+Inputs!$H$8)^(1/12)-1)) -> 98.20441 | D11: =Inputs!$B$7 -> 10000000 | E11: =D11/C11 -> 101828.42 | F11: =F10+E11 -> 798799.68 | G11: =F11*C11 -> 78445651 | H11: =H10*(1+((1+Inputs!$H$9)^(1/12)-1)) -> 105.23929 | I11: =D11 -> 10000000 | J11: =I11/H11 -> 95021.549 | K11: =K10+J11 -> 785107.37 | L11: =K11*H11 -> 82624139 | M11: =M10+D11 -> 80000000
A12: 46266 | B12: Projected | C12: =C11*(1+((1+Inputs!$H$8)^(1/12)-1)) -> 99.136251 | D12: =Inputs!$B$7 -> 10000000 | E12: =D12/C12 -> 100871.27 | F12: =F11+E12 -> 899670.95 | G12: =F12*C12 -> 89190006 | H12: =H11*(1+((1+Inputs!$H$9)^(1/12)-1)) -> 106.07848 | I12: =D12 -> 10000000 | J12: =I12/H12 -> 94269.828 | K12: =K11+J12 -> 879377.2 | L12: =K12*H12 -> 93282996 | M12: =M11+D12 -> 90000000
A13: 46296 | B13: Projected | C13: =C12*(1+((1+Inputs!$H$8)^(1/12)-1)) -> 100.07693 | D13: =Inputs!$B$7 -> 10000000 | E13: =D13/C13 -> 99923.124 | F13: =F12+E13 -> 999594.08 | G13: =F13*C13 -> 1.0003631e+08 | H13: =H12*(1+((1+Inputs!$H$9)^(1/12)-1)) -> 106.92436 | I13: =D13 -> 10000000 | J13: =I13/H13 -> 93524.054 | K13: =K12+J13 -> 972901.25 | L13: =K13*H13 -> 1.0402685e+08 | M13: =M12+D13 -> 100000000
A14: 46327 | B14: Projected | C14: =C13*(1+((1+Inputs!$H$8)^(1/12)-1)) -> 101.02654 | D14: =Inputs!$B$7 -> 10000000 | E14: =D14/C14 -> 98983.887 | F14: =F13+E14 -> 1098578 | G14: =F14*C14 -> 1.1098554e+08 | H14: =H13*(1+((1+Inputs!$H$9)^(1/12)-1)) -> 107.77699 | I14: =D14 -> 10000000 | J14: =I14/H14 -> 92784.18 | K14: =K13+J14 -> 1065685.4 | L14: =K14*H14 -> 1.1485637e+08 | M14: =M13+D14 -> 110000000
A15: 46357 | B15: Projected | C15: =C14*(1+((1+Inputs!$H$8)^(1/12)-1)) -> 101.98516 | D15: =Inputs!$B$7 -> 10000000 | E15: =D15/C15 -> 98053.478 | F15: =F14+E15 -> 1196631.4 | G15: =F15*C15 -> 1.2203865e+08 | H15: =H14*(1+((1+Inputs!$H$9)^(1/12)-1)) -> 108.63642 | I15: =D15 -> 10000000 | J15: =I15/H15 -> 92050.159 | K15: =K14+J15 -> 1157735.6 | L15: =K15*H15 -> 1.2577225e+08 | M15: =M14+D15 -> 120000000
A16: 46388 | B16: Projected | C16: =C15*(1+((1+Inputs!$H$8)^(1/12)-1)) -> 102.95288 | D16: =Inputs!$B$7 -> 10000000 | E16: =D16/C16 -> 97131.814 | F16: =F15+E16 -> 1293763.3 | G16: =F16*C16 -> 1.3319665e+08 | H16: =H15*(1+((1+Inputs!$H$9)^(1/12)-1)) -> 109.5027 | I16: =D16 -> 10000000 | J16: =I16/H16 -> 91321.945 | K16: =K15+J16 -> 1249057.5 | L16: =K16*H16 -> 1.3677518e+08 | M16: =M15+D16 -> 130000000
A17: 46419 | B17: Projected | C17: =C16*(1+((1+Inputs!$H$8)^(1/12)-1)) -> 103.92978 | D17: =Inputs!$B$7 -> 10000000 | E17: =D17/C17 -> 96218.813 | F17: =F16+E17 -> 1389982.1 | G17: =F17*C17 -> 1.4446053e+08 | H17: =H16*(1+((1+Inputs!$H$9)^(1/12)-1)) -> 110.37589 | I17: =D17 -> 10000000 | J17: =I17/H17 -> 90599.492 | K17: =K16+J17 -> 1339657 | L17: =K17*H17 -> 1.4786584e+08 | M17: =M16+D17 -> 140000000
A18: 46447 | B18: Projected | C18: =C17*(1+((1+Inputs!$H$8)^(1/12)-1)) -> 104.91595 | D18: =Inputs!$B$7 -> 10000000 | E18: =D18/C18 -> 95314.395 | F18: =F17+E18 -> 1485296.5 | G18: =F18*C18 -> 1.5583129e+08 | H18: =H17*(1+((1+Inputs!$H$9)^(1/12)-1)) -> 111.25605 | I18: =D18 -> 10000000 | J18: =I18/H18 -> 89882.755 | K18: =K17+J18 -> 1429539.8 | L18: =K18*H18 -> 1.5904495e+08 | M18: =M17+D18 -> 150000000
A19: 46478 | B19: Projected | C19: =C18*(1+((1+Inputs!$H$8)^(1/12)-1)) -> 105.91147 | D19: =Inputs!$B$7 -> 10000000 | E19: =D19/C19 -> 94418.478 | F19: =F18+E19 -> 1579714.9 | G19: =F19*C19 -> 1.6730994e+08 | H19: =H18*(1+((1+Inputs!$H$9)^(1/12)-1)) -> 112.14322 | I19: =D19 -> 10000000 | J19: =I19/H19 -> 89171.687 | K19: =K18+J19 -> 1518711.5 | L19: =K19*H19 -> 1.7031319e+08 | M19: =M18+D19 -> 160000000
A20: 46508 | B20: Projected | C20: =C19*(1+((1+Inputs!$H$8)^(1/12)-1)) -> 106.91644 | D20: =Inputs!$B$7 -> 10000000 | E20: =D20/C20 -> 93530.981 | F20: =F19+E20 -> 1673245.9 | G20: =F20*C20 -> 1.7889751e+08 | H20: =H19*(1+((1+Inputs!$H$9)^(1/12)-1)) -> 113.03746 | I20: =D20 -> 10000000 | J20: =I20/H20 -> 88466.245 | K20: =K19+J20 -> 1607177.7 | L20: =K20*H20 -> 1.8167129e+08 | M20: =M19+D20 -> 170000000
A21: 46539 | B21: Projected | C21: =C20*(1+((1+Inputs!$H$8)^(1/12)-1)) -> 107.93095 | D21: =Inputs!$B$7 -> 10000000 | E21: =D21/C21 -> 92651.827 | F21: =F20+E21 -> 1765897.8 | G21: =F21*C21 -> 1.9059503e+08 | H21: =H20*(1+((1+Inputs!$H$9)^(1/12)-1)) -> 113.93884 | I21: =D21 -> 10000000 | J21: =I21/H21 -> 87766.383 | K21: =K20+J21 -> 1694944.1 | L21: =K21*H21 -> 1.9311997e+08 | M21: =M20+D21 -> 180000000
A22: 46569 | B22: Projected | C22: =C21*(1+((1+Inputs!$H$8)^(1/12)-1)) -> 108.95509 | D22: =Inputs!$B$7 -> 10000000 | E22: =D22/C22 -> 91780.937 | F22: =F21+E22 -> 1857678.7 | G22: =F22*C22 -> 2.0240354e+08 | H22: =H21*(1+((1+Inputs!$H$9)^(1/12)-1)) -> 114.84741 | I22: =D22 -> 10000000 | J22: =I22/H22 -> 87072.058 | K22: =K21+J22 -> 1782016.2 | L22: =K22*H22 -> 2.0465993e+08 | M22: =M21+D22 -> 190000000
... A123: 49644 | B123: Projected | C123: =C122*(1+((1+Inputs!$H$8)^(1/12)-1)) -> 282.81289 | D123: =Inputs!$B$7 -> 10000000 | E123: =D123/C123 -> 35359.067 | F123: =F122+E123 -> 7803837.5 | G123: =F123*C123 -> 2.2070259e+09 | H123: =H122*(1+((1+Inputs!$H$9)^(1/12)-1)) -> 256.159 | I123: =D123 -> 10000000 | J123: =I123/H123 -> 39038.253 | K123: =K122+J123 -> 7805713.1 | L123: =K123*H123 -> 1.9995037e+09 | M123: =M122+D123 -> 1200000000
A127: DCA Summary | F127: Projection Assumptions
A128: Metric | B128: Maximum-Sharpe Portfolio | C128: VN-Index | D128: Notes | F128: Assumption | G128: Value | H128: Interpretation
A129: Investment start date | B129: =A4 -> 46023 | C129: =A4 -> 46023 | D129: Initial investment is made in Jan-2026. | F129: Future portfolio annual return | G129: =Inputs!H8 -> 0.12 | H129: Base case applied from Aug-2026 onward.
A130: Actual data through | B130: =A10 -> 46204 | C130: =A10 -> 46204 | D130: Actual fund and VN-Index returns are used through Jul-2026. | F130: Future VN-Index annual return | G130: =Inputs!H9 -> 0.1 | H130: Benchmark base case from Aug-2026 onward.
A131: Projection end date | B131: =A123 -> 49644 | C131: =A123 -> 49644 | D131: Projection runs through Dec-2035. | F131: Monthly DCA | G131: =Inputs!B7 -> 10000000 | H131: Contribution from Feb-2026 onward.
A132: Contributions through actual period | B132: =M10 -> 70000000 | C132: =M10 -> 70000000 | D132: Initial investment plus six monthly contributions. | F132: Contribution timing | G132: =Inputs!H11 -> Month-end | H132: Purchases modeled at month-end.
A133: Value at Jul-2026 | B133: =G10 -> 67802290 | C133: =L10 -> 72049606 | D133: Actual value using Jan-Jul 2026 market data.
A134: Projected total contributions | B134: =M123 -> 1200000000 | C134: =M123 -> 1200000000 | D134: Initial investment plus monthly DCA through Dec-2035.
A135: Projected ending value | B135: =G123 -> 2.2070259e+09 | C135: =L123 -> 1.9995037e+09 | D135: Based on editable future return assumptions.
A136: Projected investment gain | B136: =B135-B134 -> 1.0070259e+09 | C136: =C135-C134 -> 7.9950367e+08 | D136: Ending value less total contributions.
A137: Projected return on contributions | B137: =B135/B134-1 -> 0.83918822 | C137: =C135/C134-1 -> 0.66625306 | D137: Gain divided by total contributions.

Sheet Dashboard
A1: Vietnam Mutual Fund Portfolio Analytics Dashboard
A2: Five funds versus VN-Index | Jan 2024 – Jul 2026 | 30 monthly returns
A4: Best Fund CAGR MAGEF 19.7% | D4: Best Fund Sharpe VCBF-BCF 1.03x | G4: Max Sharpe Portfolio Expected Return 19.2% | J4: Max Sharpe Portfolio Volatility 15.5% | M4: Max Sharpe Portfolio Sharpe 0.95x | P4: VN-Index CAGR VN-Index 22.2%
A10: Asset | B10: CAGR | C10: Volatility | D10: Sharpe
A11: VESAF | B11: 0.10721502 | C11: 0.1635687 | D11: 0.38036017
A12: DCDS | B12: 0.18445662 | C12: 0.17356649 | D12: 0.80347667
A13: SSISCA | B13: 0.15474944 | C13: 0.15564429 | D13: 0.70512988
A14: VCBF-BCF | B14: 0.1901824 | C14: 0.14092402 | D14: 1.0302176
A15: MAGEF | B15: 0.19692875 | C15: 0.16975178 | D15: 0.89500531
A16: VN-Index | B16: 0.22174809 | C16: 0.16111178 | D16: 1.0970525
A17: Minimum Variance Portfolio | B17: 0.16979196 | C17: 0.14675964 | D17: 0.85031522
A18: Maximum Sharpe Portfolio | B18: 0.19173578 | C18: 0.15494997 | D18: 0.94698812
A22: Date | B22: VESAF | C22: DCDS | D22: SSISCA | E22: VCBF-BCF | F22: MAGEF | G22: VN-Index
A23: 45292 | B23: 100 | C23: 100 | D23: 100 | E23: 100 | F23: 100 | G23: 100
A24: 45323 | B24: 104.28863 | C24: 102.71558 | D24: 106.357 | E24: 104.96612 | F24: 104.53898 | G24: 103.64931
A25: 45352 | B25: 108.36872 | C25: 109.49489 | D25: 112.86915 | E25: 114.33113 | F25: 112.44202 | G25: 111.18298
A26: 45383 | B26: 114.05451 | C26: 115.36477 | D26: 119.06214 | E26: 117.18753 | F26: 117.93861 | G26: 113.23649
A27: 45413 | B27: 109.17983 | C27: 110.63897 | D27: 115.56042 | E27: 111.26772 | F27: 112.26459 | G27: 107.47888
A28: 45444 | B28: 116.70619 | C28: 120.25627 | D28: 124.95683 | E28: 119.13141 | F28: 120.30409 | G28: 113.10218
A29: 45474 | B29: 117.90121 | C29: 120.60307 | D29: 127.02543 | E29: 118.91489 | F29: 120.12795 | G29: 110.85427
A30: 45505 | B30: 118.12697 | C30: 115.98412 | D30: 127.26607 | E30: 118.54127 | F30: 117.50078 | G30: 108.41551
A31: 45536 | B31: 120.19926 | C31: 122.24653 | D31: 130.13313 | E31: 121.6504 | F31: 123.06692 | G31: 112.73106 | J31: Fund | K31: Maximum Sharpe Weight
A32: 45566 | B32: 120.49684 | C32: 122.62103 | D32: 131.19662 | E32: 124.51878 | F32: 123.62983 | G32: 114.18019 | J32: VESAF | K32: 0
A33: 45597 | B33: 119.18038 | C33: 120.42258 | D33: 129.38812 | E33: 122.35291 | F33: 121.61151 | G33: 110.88343 | J33: DCDS | K33: 0.2
A34: 45627 | B34: 118.96522 | C34: 120.29375 | D34: 129.89275 | E34: 123.68235 | F34: 120.14739 | G34: 110.55827 | J34: SSISCA | K34: 9.0205621e-17
A35: 45658 | B35: 122.23489 | C35: 123.51459 | D35: 133.48804 | E35: 127.03625 | F35: 123.09458 | G35: 112.19295 | J35: VCBF-BCF | K35: 0.4
A36: 45689 | B36: 121.41007 | C36: 122.3382 | D36: 133.11844 | E36: 125.14942 | F36: 122.69837 | G36: 110.71908 | J36: MAGEF | K36: 0.4
A37: 45717 | B37: 122.22754 | C37: 123.60057 | D37: 135.72677 | E37: 128.68499 | F37: 123.19604 | G37: 115.69735
A38: 45748 | B38: 117.4647 | C38: 121.09546 | D38: 131.9934 | E38: 124.75857 | F38: 119.49145 | G38: 116.4007
A39: 45778 | B39: 107.7887 | C39: 116.19147 | D39: 120.30312 | E39: 119.5084 | F39: 111.77679 | G39: 109.57216
A40: 45809 | B40: 114.22267 | C40: 129.47322 | D40: 128.08742 | E40: 126.83716 | F40: 118.84493 | G40: 118.07691
A41: 45839 | B41: 120.58169 | C41: 134.22322 | D41: 133.93367 | E41: 132.67328 | F41: 124.88952 | G41: 121.74743
A42: 45870 | B42: 126.26083 | C42: 148.04498 | D42: 138.8847 | E42: 141.13909 | F42: 136.59033 | G42: 132.11837
A43: 45901 | B43: 143.09658 | C43: 166.89624 | D43: 154.48937 | E43: 155.8472 | F43: 156.90601 | G43: 148.56148
A44: 45931 | B44: 136.32904 | C44: 162.49903 | D44: 151.41899 | E44: 152.85982 | F44: 155.2983 | G44: 147.12561
A45: 45962 | B45: 133.31104 | C45: 156.95771 | D45: 149.79226 | E45: 150.74716 | F45: 150.61969 | G45: 142.87986
A46: 45992 | B46: 130.58963 | C46: 157.52514 | D46: 149.4747 | E46: 151.29012 | F46: 153.80753 | G46: 150.3614
A47: 46023 | B47: 129.79571 | C47: 163.98028 | D47: 146.3221 | E47: 156.02682 | F47: 160.70271 | G47: 158.02495
A48: 46054 | B48: 142.34992 | C48: 166.6382 | D48: 159.42225 | E48: 167.38185 | F48: 168.35933 | G48: 159.62429
... A53: 46204 | B53: 128.99709 | C53: 152.68554 | D53: 143.29116 | E53: 154.53747 | F53: 156.73672 | G53: 164.98869
A56: Key Findings and Investment Interpretation
A57: 1. MAGEF delivered the strongest fund CAGR at 19.7%; however, VN-Index CAGR was 22.2% over the same short sample. 2. VCBF-BCF had the best fund-level risk-adjusted result, with a Sharpe ratio of 1.03. 3. The maximum-Sharpe portfolio allocates 20% to DCDS, 40% to VCBF-BCF and 40% to MAGEF, producing an expected return of 19.2% and volatility of 15.5%. 4. Average pairwise fund correlation was 0.89, indicating limited but still measurable diversification benefits. 5. The dataset contains only 30 monthly returns. Optimization results may be sensitive to the period and should be stress-tested with longer NAV histories.

Sheet Methodology
A1: Project Methodology, Sources and Resume Summary
A2: Documentation for reproducibility, interpretation and interview discussion.
A4: Project Objective
A5: Build an end-to-end mutual fund portfolio analytics system that cleans monthly NAV data, measures performance and risk, compares funds with VN-Index, optimizes allocation, simulates long-term outcomes and evaluates a dollar-cost-averaging strategy.
A9: Data Sources
A10: Input | B10: Source | C10: Treatment
A11: Monthly fund NAV and VN-Index | B11: User-provided workbook: CCQ giá theo tháng(1).xlsx | C11: Monthly observations; no missing rows in the supplied range.
A12: Risk-free rate | B12: Editable analyst assumption in Inputs | C12: Default 4.5% annually; replace with a documented market proxy if required.
A14: Key Formulas
A15: Monthly return | B15: NAV(t) / NAV(t-1) - 1
A16: CAGR | B16: (Ending / Beginning)^(12 / number of monthly returns) - 1
A17: Annualized volatility | B17: STDEV.S(monthly returns) × √12
A18: Sharpe ratio | B18: (CAGR - risk-free rate) / annualized volatility
A19: Beta | B19: Covariance(fund, VN-Index) / Variance(VN-Index)
A20: Max drawdown | B20: Minimum of Growth Index / Running Peak - 1
A21: Portfolio volatility | B21: √(w'Σw)
A22: Optimization | B22: SLSQP; long-only; weights sum to 100%; maximum weight 40%.
A23: Monte Carlo | B23: Geometric-Brownian-style monthly return process with fixed random seed and monthly contributions.
A25: Limitations
A26: • Only 31 monthly NAV observations are available; this is insufficient to represent a full market cycle. • Historical CAGR and covariance are unstable estimates and do not guarantee future performance. • Fund fees, subscription/redemption charges, taxes and tracking differences are not modeled. • Monte Carlo assumes a stable return distribution and does not explicitly model regime changes or fat tails. • The optimized portfolios should be stress-tested under alternative assumptions and longer histories.
A32: Resume-Ready Project Summary
A33: Vietnam Mutual Fund Portfolio Analytics | Excel, Python, Portfolio Optimization • Built an end-to-end analytics model for five Vietnamese mutual funds and VN-Index, calculating CAGR, volatility, Sharpe ratio, beta, alpha, tracking error, correlation and maximum drawdown. • Applied constrained portfolio optimization to construct minimum-variance and maximum-Sharpe allocations and generated an efficient frontier under long-only 0%–40% position limits. • Developed a 5,000-path, 10-year Monte Carlo simulation and historical DCA analysis to evaluate portfolio value distributions, downside probability and benchmark-relative outcomes. • Designed an interactive Excel dashboard with editable assumptions, automated formulas and investment insights.
A41: DCA Timeline and Projection Method
A42: Item | B42: Treatment | C42: Default assumption
A43: Start date | B43: Initial investment is made in Jan-2026. | C43: Jan-2026
A44: Actual period | B44: Actual monthly fund and VN-Index returns are used. | C44: Jan-2026 to Jul-2026
A45: Projection period | B45: A constant equivalent monthly return is derived from the annual assumption. | C45: Aug-2026 to Dec-2035
A46: Portfolio return assumption | B46: Editable in Inputs; applied only to projected months. | C46: 12.0% annually
A47: VN-Index return assumption | B47: Editable in Inputs; applied only to projected months. | C47: 10.0% annually
